Workbook

Sheet README
A1: Project Southeast Asia — Trading Comparables
A2: Independent student analysis/reconstruction based on publicly available information. Not affiliated with, commissioned by, or representative of Goldman Sachs or AkzoNobel.
A4: DATA SOURCE UPDATE (2026-09-18): This tab was rebuilt using live market data pulled via the Yahoo Finance API (yfinance) for all seven companies in a single pass, replacing the original secondary-aggregator dataset built in Phase 4. This resolves every data-quality issue previously flagged: PPG's EV/EBITDA (previously unavailable) is now populated; Berger Paints' EV/EBITDA (previously an internally inconsistent 36.8x figure, left blank) now has a coherent, consistent 28.3x figure; Kansai Paint's currency mismatch is resolved (EV and revenue now both sourced in JPY from the same feed); and every company's market cap now reflects a single consistent pull rather than conflicting figures from different aggregators on different dates.
A6: METHODOLOGY: All figures pulled via yfinance (Yahoo Finance's data feed) on 2026-09-18. Market Cap, Enterprise Value, Revenue (TTM), EBITDA (TTM), Beta and derived multiples (EV/Revenue, EV/EBITDA) are as reported by Yahoo Finance for each ticker at the time of the pull. This is real, live market data — not an illustrative assumption — but it is still a single secondary data provider's aggregation, not a licensed institutional terminal (Bloomberg/CapIQ/Refinitiv), and Yahoo's EBITDA figure may reflect unadjusted (GAAP) EBITDA rather than a company's own disclosed 'adjusted EBITDA' measure — see the AkzoNobel note below for a specific instance of this distinction.
A8: AKZONOBEL NOTE: Yahoo Finance's feed shows AkzoNobel FY revenue of ~EUR9.89bn and EBITDA margin of ~10.8% — these differ from AkzoNobel's own disclosed FY2025 figures used elsewhere in this project (revenue EUR10.158bn, adjusted EBITDA margin 15.8%, per AkzoNobel's own Q4 2025 results release, SRC-013/SRC-015) because Yahoo's EBITDA is an unadjusted/trailing calculation while AkzoNobel's own disclosure is an adjusted, company-defined metric excluding one-off items. AkzoNobel's own disclosed figures remain PUBLIC FACT and are used elsewhere in this project (e.g., 02_Financial_Model's EBITDA margin proxy); the Yahoo-sourced figures below are shown for cross-referencing on this tab only and AkzoNobel is still excluded from peer statistics as the seller.
A10: COMPARABILITY notes carried forward from Phase 4 are unchanged — see the Comps tab for buyer/peer comparability commentary (Nippon Paint/Kansai Paint = strongest regional comparability; Asian Paints/Berger = closest business-mix comparability; Sherwin-Williams/PPG = large-cap developed-market comparability only; AkzoNobel = seller, reference only).

Sheet Comps
A1: Trading Comparables — Paints & Coatings Sector (live data, 2026-09-18)
A2: Figures in company's reporting currency. Source: Yahoo Finance (yfinance), single consistent pull, 2026-09-18.
A4: Company | B4: Currency | C4: Market Cap (mm) | D4: Enterprise Value (mm) | E4: Revenue TTM (mm) | F4: EBITDA TTM (mm) | G4: EBITDA Margin % | H4: EV / Revenue | I4: EV / EBITDA | J4: Beta | K4: P/E (TTM) | L4: Classification | M4: Source
A5: Sherwin-Williams | B5: USD | C5: 77920.5 | D5: 92316.5 | E5: 24410.3 | F5: 4709.1 | G5: =F5/E5 | H5: =D5/E5 | I5: =D5/F5 | J5: 1.089 | K5: 29.64 | L5: Large-cap, developed-market (NA-weighted) diversified coatings player. Limited direct SEA comparability given scale/geography. | M5: Yahoo Finance (yfinance), pulled 2026-09-18 (ticker: SHW)
A6: PPG Industries | B6: USD | C6: 23439.3 | D6: 29345.1 | E6: 16421 | F6: 2698 | G6: =F6/E6 | H6: =D6/E6 | I6: =D6/F6 | J6: 1.063 | K6: 15.13 | L6: Large-cap, developed-market diversified coatings player. Limited direct SEA comparability given scale/geography. | M6: Yahoo Finance (yfinance), pulled 2026-09-18 (ticker: PPG)
A7: Nippon Paint Holdings | B7: JPY | C7: 2680136.7 | D7: 3641233.6 | E7: 1945486 | F7: 361080 | G7: =F7/E7 | H7: =D7/E7 | I7: =D7/F7 | J7: 0.821 | K7: 18.35 | L7: Japan-HQ, meaningful APAC/decorative exposure incl. confirmed SEA market share. Strong comparability. | M7: Yahoo Finance (yfinance), pulled 2026-09-18 (ticker: 4612.T)
A8: Kansai Paint | B8: JPY | C8: 513356.4 | D8: 701160.3 | E8: 602968 | F8: 77297.7 | G8: =F8/E8 | H8: =D8/E8 | I8: =D8/F8 | J8: n/a | K8: 19.49 | L8: Japan-HQ, APAC/decorative exposure. Reasonably comparable. | M8: Yahoo Finance (yfinance), pulled 2026-09-18 (ticker: 4613.T)
A9: Asian Paints | B9: INR | C9: 2352513 | D9: 2313578.1 | E9: 371869.3 | F9: 68878.9 | G9: =F9/E9 | H9: =D9/E9 | I9: =D9/F9 | J9: 0.282 | K9: 49.3 | L9: India-listed decorative-paints pure-play, EM growth profile similar to target. Most comparable on business mix. | M9: Yahoo Finance (yfinance), pulled 2026-09-18 (ticker: ASIANPAINT.NS)
A10: Berger Paints India | B10: INR | C10: 523068.9 | D10: 516758.2 | E10: 122632.4 | F10: 18228.5 | G10: =F10/E10 | H10: =D10/E10 | I10: =D10/F10 | J10: 0.441 | K10: 42.97 | L10: India-listed decorative-paints pure-play (Asian Paints group), EM growth profile similar to target. Most comparable on business mix. | M10: Yahoo Finance (yfinance), pulled 2026-09-18 (ticker: BERGEPAINT.NS)
A11: AkzoNobel (AKZA.AS) — SELLER, reference only | B11: EUR | C11: 9684.1 | D11: 13169.4 | E11: 9894 | F11: 1068 | G11: =F11/E11 | H11: =D11/E11 | I11: =D11/F11 | J11: 1.179 | K11: 15.19 | L11: SELLER — excluded from percentile stats. NOTE: Yahoo's unadjusted EBITDA (EUR1,068mm) differs from AkzoNobel's own disclosed FY2025 adjusted EBITDA (~EUR1,444mm at 15.8% margin on EUR4.09bn Decorative Paints segment revenue) — see README. | M11: Yahoo Finance (yfinance), pulled 2026-09-18 (ticker: AKZA.AS)
A13: Summary Statistics (all 6 peers now complete — single-source live data, no exclusions needed)
A14: Statistic | H14: EV / Revenue | I14: EV / EBITDA | J14: Beta
A15: 25th percentile | H15: =QUARTILE(N20:N25,1) | I15: =QUARTILE(O20:O25,1) | J15: =QUARTILE(P20:P24,1)
A16: Median | H16: =MEDIAN(N20:N25) | I16: =MEDIAN(O20:O25) | J16: =MEDIAN(P20:P24)
A17: 75th percentile | H17: =QUARTILE(N20:N25,3) | I17: =QUARTILE(O20:O25,3) | J17: =QUARTILE(P20:P24,3)
N19: Peer set: EV/Revenue | O19: Peer set: EV/EBITDA | P19: Peer set: Beta
N20: =H5 | O20: =I5 | P20: =J5
N21: =H6 | O21: =I6 | P21: =J6
N22: =H7 | O22: =I7 | P22: =J7
N23: =H8 | O23: =I8 | P23: =J9
N24: =H9 | O24: =I9 | P24: =J10
N25: =H10 | O25: =I10

Sheet Implied_Valuation
A1: Implied Valuation — SEA Decorative Paints Carve-Out (from Trading Comps)
A2: Applies Comps tab EV/Revenue and EV/EBITDA percentiles (now computed from a complete, consistent 6-company live dataset) to the carve-out model's FY2026E revenue and EBITDA (see 02_Financial_Model).
A4: SEA Carve-Out FY2026E Revenue (EUR mm) — from financial model | B4: 315
A5: SEA Carve-Out FY2026E EBITDA (EUR mm) — from financial model | B5: 52
A7: Methodology | B7: Low (25th pct) | C7: Mid (Median) | D7: High (75th pct)
A8: EV / Revenue multiple (from Comps tab) | B8: =Comps!H15 | C8: =Comps!H16 | D8: =Comps!H17
A9: Implied EV — Revenue basis (EUR mm) | B9: =B8*$B$4 | C9: =C8*$B$4 | D9: =D8*$B$4
A11: EV / EBITDA multiple (from Comps tab) | B11: =Comps!I15 | C11: =Comps!I16 | D11: =Comps!I17
A12: Implied EV — EBITDA basis (EUR mm) | B12: =B11*$B$5 | C12: =C11*$B$5 | D12: =D11*$B$5
A14: UPDATE (2026-09-18): This range now derives from a complete, single-source, same-day dataset across all 6 peers (previously 3-4 usable data points per basis, with known cross-source inconsistencies). The range is narrower and more defensible than the Phase 4 version, though it should still be triangulated against the DCF (02_Financial_Model) and precedent transactions (04_Precedent_Transactions) — see 05_Valuation.
