Workbook

Sheet README
A1: Project Southeast Asia — Valuation Triangulation
A2: Independent student analysis/reconstruction based on publicly available information. Not affiliated with, commissioned by, or representative of Goldman Sachs or AkzoNobel.
A4: PURPOSE: Brings together the three valuation methodologies built in prior phases — DCF (02_Financial_Model), Trading Comparables (03_Trading_Comps) and Precedent Transactions (04_Precedent_Transactions) — into a single triangulated Enterprise Value range for the SEA decorative paints carve-out, with an Enterprise-to-Equity bridge and explicit sensitivity analysis.
A6: INPUTS ARE HARDCODED FROM PRIOR-PHASE WORKBOOKS (not live cross-file links, since each workbook is a separate file): every pulled figure cites which workbook/tab it was taken from. If an upstream assumption changes, this workbook must be manually refreshed to match — this is flagged as a manual-refresh dependency, not a live model chain.
A8: DATA REFRESH (2026-09-18): WACC's beta input and all Trading Comps figures were updated from illustrative/aggregator placeholders to live market data (Yahoo Finance via yfinance, single consistent pull across all 6 peers) after this workbook was first built. The figures below reflect that refresh — see 03_Trading_Comps/README and 02_Financial_Model/Assumptions (beta row) for full methodology.
A10: HEADLINE RESULT: The three methodologies do NOT converge tightly — see Triangulation tab. DCF centers around EUR 613mm (range EUR 468-908mm across WACC/terminal-growth sensitivity), using a WACC of 8.88% built with a real peer-median beta of 0.821. Trading comps (now complete across all 6 peers with no exclusions) imply a higher range (EUR 535-1,360mm) still influenced by Asian Paints' rich 33.6x EV/EBITDA multiple. Precedent transactions imply the widest range in relative terms (EUR 87-690mm), spanning a low-margin PE-sponsor carve-out at one end and a rejected strategic mega-offer at the other. This dispersion is a genuine finding, not a modeling error — it reflects how little hard, comparable public data exists for this specific carve-out. A recommended primary range is presented on the Triangulation tab with explicit reasoning for which data points are weighted and which are treated as outlier context only.
A12: See Triangulation tab for the football-field summary and Equity_Bridge tab for the EV-to-equity walk (equity value cannot be calculated — see limitation there).

Sheet DCF_Summary
A1: DCF Valuation Summary (recap of 02_Financial_Model/DCF_Valuation)
A2: Base case: WACC 8.88% (beta 0.821, live peer median, 2026-09-18), terminal growth 3.0%. See 02_Financial_Model for full build.
A4: Base case Enterprise Value (EUR mm) | B4: 613
A5: TV as % of EV | B5: 0.787
A7: Sensitivity: Enterprise Value (EUR mm) — WACC x Terminal Growth
A8: WACC \ g | B8: 0.02 | C8: 0.025 | D8: 0.03 | E8: 0.035 | F8: 0.04
A9: 0.07877 | B9: 635 | C9: 684.2 | D9: 743.5 | E9: 816.3 | F9: 907.9
A10: 0.08377 | B10: 583.3 | C10: 624 | D10: 672.3 | E10: 730.5 | F10: 802
A11: 0.08877 | B11: 539.1 | C11: 573.3 | D11: 613.3 | E11: 660.7 | F11: 717.8
A12: 0.09377 | B12: 501 | C12: 530 | D12: 563.5 | E12: 602.8 | F12: 649.3
A13: 0.09877 | B13: 467.7 | C13: 492.5 | D13: 521 | E13: 554 | F13: 592.5
A15: DCF-implied range (min / base / max, EUR mm) | B15: =MIN(B9:F13) | C15: 613 | D15: =MAX(B9:F13)

Sheet Trading_Comps_Summary
A1: Trading Comps Valuation Summary (recap of 03_Trading_Comps)
A2: SEA carve-out FY2026E: Revenue EUR 315mm, EBITDA EUR 52mm (02_Financial_Model).
A4: Basis | B4: Low (P25) | C4: Mid (Median) | D4: High (P75)
A5: EV / Revenue multiple | B5: 1.81 | C5: 2.83 | D5: 4.11
A6: Implied EV — Revenue basis (EUR mm) | B6: 570 | C6: 890 | D6: 1293
A8: EV / EBITDA multiple | B8: 10.28 | C8: 15.24 | D8: 26.16
A9: Implied EV — EBITDA basis (EUR mm) | B9: 535 | C9: 792 | D9: 1360
A11: UPDATED 2026-09-18: figures now sourced from a complete, single-pull, live 6-peer dataset (Yahoo Finance via yfinance) — see 03_Trading_Comps/README. The EBITDA-basis range is still influenced by Asian Paints' 33.6x EV/EBITDA multiple, but every one of the 6 peers now has a usable figure (vs. 3-4 previously), so the percentile statistics are more robust than the original aggregator-sourced version.

Sheet Precedent_Summary
A1: Precedent Transactions Valuation Summary (recap of 04_Precedent_Transactions)
A2: SEA carve-out FY2026E Revenue EUR 315mm.
A4: Basis | B4: Low (PPG/AIP) | C4: Mid (SHW/Suvinil) | D4: High (Nippon/AkzoNobel, rejected offer)
A5: EV / Revenue multiple applied | B5: 0.275 | C5: 2.19 | D5: 1.83
A6: Implied EV (EUR mm) | B6: 87 | C6: 690 | D6: 578
A8: JSW/AkzoNobel India (25x EBITDA) is excluded from this range — India-specific control-premium dynamics not representative of a SEA multi-country carve-out. Nippon Paint/Vibgyor excluded — value undisclosed.

Sheet Triangulation
A1: Valuation Triangulation — Enterprise Value (EUR mm)
A2: All figures recapped from the DCF_Summary, Trading_Comps_Summary and Precedent_Summary tabs of this workbook.
A4: Methodology | B4: Low | C4: Mid | D4: High | E4: Notes
A5: DCF (unlevered FCF, WACC/g sensitivity) | B5: =DCF_Summary!B15 | C5: =DCF_Summary!C15 | D5: =DCF_Summary!D15 | F5: Base case anchor; WACC 7.88%-9.88% (beta 0.821, live peer median) x terminal growth 2.0%-4.0% sensitivity range.
A6: Trading Comps — EV/Revenue basis | B6: =Trading_Comps_Summary!B6 | C6: =Trading_Comps_Summary!C6 | D6: =Trading_Comps_Summary!D6 | F6: P25/Median/P75 across all 6 peers (Sherwin-Williams, PPG, Nippon Paint, Kansai Paint, Asian Paints, Berger Paints) — complete dataset, live pull 2026-09-18.
A7: Trading Comps — EV/EBITDA basis | B7: =Trading_Comps_Summary!B9 | C7: =Trading_Comps_Summary!C9 | D7: =Trading_Comps_Summary!D9 | F7: Same complete 6-peer dataset; still influenced by Asian Paints' 33.6x — treat with some caution.
A8: Precedent Transactions | B8: =Precedent_Summary!B6 | C8: =Precedent_Summary!C6 | D8: =Precedent_Summary!D6 | F8: PPG/AIP (floor) to SHW/Suvinil (closest structural match) to Nippon/AkzoNobel rejected offer (strategic ceiling).
A10: RECOMMENDED PRIMARY RANGE (analyst judgment) | B10: 500 | C10: 625 | D10: 775 | F10: ANALYST CALCULATION / JUDGMENT — see rationale below. Not a disclosed or confirmed figure. Updated 2026-09-18.
A12: RATIONALE FOR RECOMMENDED RANGE (updated 2026-09-18 following a live-data refresh of beta and trading comps): Anchored primarily on the DCF base case (EUR 613mm, now using a WACC of 8.88% built with a real peer-median beta of 0.821 in place of the original illustrative 1.00) and its own sensitivity band, cross-checked against the two most structurally comparable data points available — the Sherwin-Williams/BASF Suvinil precedent (EUR 690mm, the closest deal structurally: a global strategic buying a single-country emerging-market decorative paints carve-out from another major) and the Nippon Paint/AkzoNobel Decorative Paints rejected offer (EUR 578mm on a like-for-like revenue basis, though that offer was for the GLOBAL segment and was never consummated). The trading comps EV/EBITDA range (EUR 535-1,360mm) and EV/Revenue range (EUR 570-1,293mm) are now computed across a complete, single-source, same-day 6-peer dataset (no exclusions) but are still treated as directional upside context rather than primary drivers, given the outsized influence of Asian Paints' India-specific premium multiple (33.6x EV/EBITDA). The PPG/AIP precedent (EUR 87mm) is treated as a low-margin financial-sponsor floor case, not representative of a strategic-buyer process for a growing SEA decorative platform. The JSW/AkzoNobel India precedent (25x EBITDA, implying a much higher EV than any range shown here) is excluded as an India-specific outlier not comparable to a multi-country SEA carve-out — see 04_Precedent_Transactions for full reasoning. This range should be treated as illustrative and provisional: it rests on a financial model built almost entirely from ILLUSTRATIVE ASSUMPTIONS for the carve-out P&L (see 02_Financial_Model/README), even though the WACC beta and trading comps inputs are now real, live market data.
A14: (chart helper — base)
H15: Label | I15: Base (=Low, hidden) | J15: Range (High-Low, visible)
H16: =A5 | I16: =B5 | J16: =D5-B5
H17: =A6 | I17: =B6 | J17: =D6-B6
H18: =A7 | I18: =B7 | J18: =D7-B7
H19: =A8 | I19: =B8 | J19: =D8-B8
H20: =A10 | I20: =B10 | J20: =D10-B10

Sheet Equity_Bridge
A1: Enterprise Value to Equity Value Bridge
A3: Recommended Enterprise Value — Mid (EUR mm) | B3: =Triangulation!C10
A4: Less: Debt (asset-level, SEA carve-out) | B4: N/A — not publicly disclosed
A5: Plus: Cash (asset-level, SEA carve-out) | B5: N/A — not publicly disclosed
A6: Equity Value | B6: Cannot be calculated
A8: LIMITATION: AkzoNobel does not publicly disclose asset-level debt or cash for the SEA decorative paints carve-out — these exist only at the consolidated AkzoNobel Group level (Group net debt/EBITDA disclosed at 2.0x for FY2025, per AkzoNobel's Q4 2025 results release) and cannot be responsibly allocated to this specific perimeter without non-public carve-out balance sheet data. In a real sell-side process, the carve-out balance sheet (including any debt-free/cash-free convention typical of a divestiture) would be defined in the transaction structuring, not estimated by an outside analyst. Enterprise Value is therefore presented throughout this project as the primary valuation output.
