Workbook

Sheet README
A1: Project Southeast Asia — v2 Financial Model (post-announcement)
A2: Independent student analysis/reconstruction based on publicly available information. Not affiliated with, commissioned by, or representative of Goldman Sachs, AkzoNobel or Nippon Paint.
A4: WHAT THIS IS: a rebuild of the September carve-out model on the announced perimeter (seven countries) and the reported FY2024-FY2025 financials. The September files in folders 01-10 are unchanged and remain the pre-announcement record.
A5: THE ANNOUNCED PRICE IS A CHECK, NOT A TARGET. No assumption was tuned to reach EUR 1.2bn. The 'What you need to believe' block on DCF_Valuation and on each case shows what it would take.
A6: WHAT CHANGED vs September: (1) seven countries; (2) FY2024-FY2025 are reported figures, not back-solved from an anchor; (3) three cases selected on Assumptions; (4) tax and country risk premium now weighted across seven countries; (5) a normalised terminal year, a terminal-margin sensitivity and a reverse DCF; (6) FX is one input cell.
A7: SHEETS: Assumptions (inputs, selector) | Case_Drivers (growth and margin for Base / Buyer / Downside) | Revenue_Build | Working_Capital | Capex_DA | Carveout_PnL | DCF_Valuation (active case) | Cases (all three cases side by side, plus an integrity check) | Sources.
A8: CASES: Base = seller / standalone view (reported FY2025 margin held, ~5% growth). Buyer = Nippon Paint's 2026 projection (single-source, buyer's view) then a fade. Downside = 3% growth and a standalone-cost margin step-down. Rationales are on Case_Drivers.
A9: COLOUR CODE: blue = hard-coded input; black = formula; green = link to another sheet; yellow fill = key output or input to scrutinise first. CLASSIFICATIONS: PUBLIC FACT, REPORTED (corroborated or single-source), ANALYST CALCULATION, ILLUSTRATIVE ASSUMPTION, UNAVAILABLE.
A10: REPORTED FINANCIALS: FY2024-FY2025 revenue and EBITDA are NOT in AkzoNobel's release. They are reported by PCI Magazine and, attributed to Nippon Paint's own statement, by Investing.com, Yahoo Finance UK and Yahoo Finance Singapore. The primary Nippon Paint release was not accessed, so these stay REPORTED, not PUBLIC FACT. The 2026 revenue (>~USD 330m) and ~26% margin are single-source (PCI).
A11: STANDALONE COST RISK: AkzoNobel keeps Global Business Services. TSA and stranded costs are shown inside the case margin (they do not reduce EBITDA a second time); the allowance for standalone-cost risk is the Downside margin step-down.
A12: LIMITATIONS: country split and country risk premiums are illustrative; the reported margin may or may not be on a standalone basis (unknown); working-capital, D&A, capex and separation costs are unchanged illustrative inputs; comps data in the Valuation workbook are dated 2026-09-18; no equity value can be derived (net debt of the perimeter is not disclosed).

Sheet Assumptions
A1: Assumptions (v2, post-announcement)
A2: Blue = hard-coded input; black = formula; green = link to another sheet. Every input carries a classification and a source or rationale. The announced price is a CHECK in the Valuation workbook; no input below was tuned to it.
A4: Assumption | B4: Value | C4: Classification | D4: Source / rationale
A6: 1. Announced transaction (AkzoNobel release, 5 Oct 2026)
A7: FX: USD per EUR (release-implied) — the ONE FX input used everywhere | B7: 1.125 | C7: PUBLIC FACT (derived) | D7: USD 1.35bn / EUR 1.20bn from the AkzoNobel release (SRC-037). Single input cell; every USD-to-EUR conversion in the project divides by it.
A8: Check: announced EV in USD / announced EV in EUR | B8: =B9/B10 -> 1.125 | C8: ANALYST CALCULATION | D8: Must equal the FX input above.
A9: Announced enterprise value (USD m) | B9: 1350 | C9: PUBLIC FACT | D9: AkzoNobel media release (SRC-037) and Form 6-K (SRC-038): 'approximately USD 1.35 billion'.
A10: Announced enterprise value (EUR m) | B10: 1200 | C10: PUBLIC FACT | D10: Same sources: 'approximately EUR 1.20 billion'.
A11: Announced EV / FY2025 EBITDA (x), as stated by AkzoNobel | B11: 21 | C11: PUBLIC FACT | D11: AkzoNobel release (SRC-037): 21x FY25 EBITDA.
A12: Net cash proceeds after taxes and minority partners (USD m) | B12: 1000 | C12: PUBLIC FACT | D12: AkzoNobel release (SRC-037): 'approximately USD 1 billion'.
A13: Net cash proceeds after taxes and minority partners (EUR m) | B13: 900 | C13: PUBLIC FACT | D13: AkzoNobel release (SRC-037): 'approximately EUR 0.9 billion'.
A14: Nippon Paint's stated multiple on projected 2026 EBITDA (x) | B14: 16 | C14: REPORTED — corroborated | D14: 'Roughly 16 times projected 2026 EBITDA' per Nippon Paint, reported by Investing.com (SRC-041) and Yahoo Finance UK (SRC-043). Primary Nippon Paint release not accessed.
A15: Perimeter | B15: Decorative Paints, 7 countries: Vietnam, Indonesia, Malaysia, Thailand, Singapore, Papua New Guinea, Australia | C15: PUBLIC FACT | D15: AkzoNobel release (SRC-037). AkzoNobel retains Coatings and Global Business Services, so standalone cost risk is real (see Case_Drivers).
A16: Closing | B16: Indonesia late 2026; remaining transactions mid-2027; subject to regulatory approvals | C16: PUBLIC FACT | D16: AkzoNobel release (SRC-037); Nippon Paint statement per SRC-042.
A18: 2. Reported financials of the divested businesses (USD m) — NOT in AkzoNobel's release
A19: Revenue FY2024 (USD m) | B19: 299 | C19: REPORTED — corroborated | D19: PCI Magazine (SRC-039) and Yahoo Finance Singapore / MT Newswires (SRC-042), the latter attributing it to the Nippon Paint press release. Primary release not accessed; AkzoNobel's own release states no revenue.
A20: Revenue FY2025 (USD m) | B20: 291 | C20: REPORTED — corroborated | D20: PCI Magazine (SRC-039); Investing.com (SRC-041), Yahoo Finance UK (SRC-043) and Yahoo Finance Singapore (SRC-042), each attributing to Nippon Paint.
A21: EBITDA FY2024 (USD m) | B21: 69 | C21: REPORTED — corroborated | D21: As revenue FY2024 (SRC-039, SRC-042).
A22: EBITDA FY2025 (USD m) | B22: 65 | C22: REPORTED — corroborated | D22: As revenue FY2025. Also consistent with AkzoNobel's own '21x' on USD 1.35bn (1,350 / 21 = 64.3).
A23: EBITDA margin FY2024 (reported ~23%) | B23: =B21/B19 -> 0.23076923 | C23: ANALYST CALCULATION | D23: EBITDA / revenue from the two reported figures.
A24: EBITDA margin FY2025 (reported ~22%) | B24: =B22/B20 -> 0.2233677 | C24: ANALYST CALCULATION | D24: EBITDA / revenue; matches the reported ~22%.
A25: Revenue FY2024 (EUR m) | B25: =B19/B7 -> 265.77778 | C25: ANALYST CALCULATION | D25: USD / FX input.
A26: Revenue FY2025 (EUR m) | B26: =B20/B7 -> 258.66667 | C26: ANALYST CALCULATION | D26: USD / FX input.
A27: EBITDA FY2024 (EUR m) | B27: =B21/B7 -> 61.333333 | C27: ANALYST CALCULATION | D27: USD / FX input.
A28: EBITDA FY2025 (EUR m) | B28: =B22/B7 -> 57.777778 | C28: ANALYST CALCULATION | D28: USD / FX input.
A29: Nippon Paint 2026 projection: revenue (USD m, 'above ~330') | B29: 330 | C29: REPORTED — single source | D29: PCI Magazine only (SRC-039). The text says 'above ~USD 330m'; the floor is used. Buyer's view, not a seller forecast.
A30: Nippon Paint 2026 projection: EBITDA margin | B30: 0.26 | C30: REPORTED — single source | D30: PCI Magazine only (SRC-039); '~26%'.
A31: Implied Nippon Paint 2026E EBITDA (USD m) | B31: =B29*B30 -> 85.8 | C31: ANALYST CALCULATION | D31: Revenue x margin.
A32: Check: announced EV / implied 2026E EBITDA | B32: =B9/B31 -> 15.734266 | C32: ANALYST CALCULATION | D32: Compare with the corroborated 'roughly 16x': agreement supports the 2026 projection arithmetically (it does not verify the revenue figure).
A34: 3. Case selector
A35: ACTIVE CASE (1 = Base, 2 = Buyer, 3 = Downside) | B35: 1 | C35: ILLUSTRATIVE ASSUMPTION | D35: Drives Revenue_Build, Carveout_PnL and DCF_Valuation. The Cases sheet always shows all three, so the valuation workbook does not depend on this switch.
A36: Active case name | B36: =CHOOSE(B35,"Base","Buyer","Downside") -> Base | C36: ANALYST CALCULATION
A38: 4. Country split (NOT DISCLOSED) — seven countries
A39: September four-country split: Indonesia | B39: 0.4 | C39: ILLUSTRATIVE ASSUMPTION | D39: From 02_Financial_Model (illustrative then, illustrative now). Used only as the starting point for the rescaling below.
A40: September four-country split: Thailand | B40: 0.25 | C40: ILLUSTRATIVE ASSUMPTION | D40: As above.
A41: September four-country split: Vietnam | B41: 0.2 | C41: ILLUSTRATIVE ASSUMPTION | D41: As above.
A42: September four-country split: Malaysia | B42: 0.15 | C42: ILLUSTRATIVE ASSUMPTION | D42: As above.
A43: Added market share: Australia | B43: 0.08 | C43: ILLUSTRATIVE ASSUMPTION | D43: No disclosure. Australia is the largest of the three added markets by income level; a modest weight is assumed. Together with Singapore and PNG the added markets are 15% of revenue (see sensitivity note).
A44: Added market share: Singapore | B44: 0.05 | C44: ILLUSTRATIVE ASSUMPTION | D44: No disclosure; small, high-income market.
A45: Added market share: Papua New Guinea | B45: 0.02 | C45: ILLUSTRATIVE ASSUMPTION | D45: No disclosure; smallest market.
A46: Combined share of the three added markets | B46: =B43+B44+B45 -> 0.15 | C46: ANALYST CALCULATION | D46: The four original markets are rescaled to (1 - this).
A48: Revenue split by country | B48: Split | C48: Classification | D48: Derivation
A49: Indonesia | B49: =B39*(1-B46) -> 0.34 | C49: ILLUSTRATIVE ASSUMPTION | D49: September split x (1 - added-market share).
A50: Thailand | B50: =B40*(1-B46) -> 0.2125 | C50: ILLUSTRATIVE ASSUMPTION | D50: September split x (1 - added-market share).
A51: Vietnam | B51: =B41*(1-B46) -> 0.17 | C51: ILLUSTRATIVE ASSUMPTION | D51: September split x (1 - added-market share).
A52: Malaysia | B52: =B42*(1-B46) -> 0.1275 | C52: ILLUSTRATIVE ASSUMPTION | D52: September split x (1 - added-market share).
A53: Australia | B53: =B43 -> 0.08 | C53: ILLUSTRATIVE ASSUMPTION | D53: Direct input above.
A54: Singapore | B54: =B44 -> 0.05 | C54: ILLUSTRATIVE ASSUMPTION | D54: Direct input above.
A55: Papua New Guinea | B55: =B45 -> 0.02 | C55: ILLUSTRATIVE ASSUMPTION | D55: Direct input above.
A56: Check: splits sum to 100% | B56: =SUM(B49:B55) -> 1 | C56: ANALYST CALCULATION
A58: Statutory corporate income tax rate | B58: Rate | C58: Classification | D58: Source
A59: Indonesia | B59: 0.22 | C59: PUBLIC FACT | D59: OECD / Trading Economics 2026 (SRC-016).
A60: Thailand | B60: 0.2 | C60: PUBLIC FACT | D60: Thaicore / OECD 2026 (SRC-016).
A61: Vietnam | B61: 0.2 | C61: PUBLIC FACT | D61: Trading Economics / OECD 2026 (SRC-016).
A62: Malaysia | B62: 0.24 | C62: PUBLIC FACT | D62: Trading Economics / OECD 2026 (SRC-016).
A63: Australia | B63: 0.3 | C63: PUBLIC FACT | D63: ATO company tax rates 2025-26 (SRC-046): 30% for companies other than base-rate entities (the 25% rate needs aggregated turnover under A$50m).
A64: Singapore | B64: 0.17 | C64: PUBLIC FACT | D64: IRAS corporate income tax rates (SRC-044): flat 17%. Exemptions and rebates are not modelled.
A65: Papua New Guinea | B65: 0.3 | C65: PUBLIC FACT | D65: PwC Tax Summaries, PNG (SRC-045): 30% for resident companies (non-resident branches 48%; a locally incorporated subsidiary is assumed).
A66: Blended statutory tax rate (revenue-weighted) | B66: =SUMPRODUCT(B49:B55,B59:B65) -> 0.2204 | C66: ANALYST CALCULATION | D66: Statutory rates only; no incentives, holidays, withholding taxes or transfer-pricing effects (none disclosed).
A68: Country risk premium (CRP) by country | B68: CRP | C68: Classification | D68: Rationale
A69: Indonesia | B69: 0.02 | C69: ILLUSTRATIVE ASSUMPTION | D69: Tier 3 (frontier-leaning EM). Tiers (0 / 1 / 2 / 4%) are an analyst ordering by general sovereign risk, NOT a published table; replace with a sourced CRP (e.g. Damodaran) when available. The September blended 1.5% is reproduced approximately by this scheme on the old four-country split (1.6%).
A70: Thailand | B70: 0.01 | C70: ILLUSTRATIVE ASSUMPTION | D70: Tier 2 (upper-middle). Tiers (0 / 1 / 2 / 4%) are an analyst ordering by general sovereign risk, NOT a published table; replace with a sourced CRP (e.g. Damodaran) when available. The September blended 1.5% is reproduced approximately by this scheme on the old four-country split (1.6%).
A71: Vietnam | B71: 0.02 | C71: ILLUSTRATIVE ASSUMPTION | D71: Tier 3. Tiers (0 / 1 / 2 / 4%) are an analyst ordering by general sovereign risk, NOT a published table; replace with a sourced CRP (e.g. Damodaran) when available. The September blended 1.5% is reproduced approximately by this scheme on the old four-country split (1.6%).
A72: Malaysia | B72: 0.01 | C72: ILLUSTRATIVE ASSUMPTION | D72: Tier 2. Tiers (0 / 1 / 2 / 4%) are an analyst ordering by general sovereign risk, NOT a published table; replace with a sourced CRP (e.g. Damodaran) when available. The September blended 1.5% is reproduced approximately by this scheme on the old four-country split (1.6%).
A73: Australia | B73: 0 | C73: ILLUSTRATIVE ASSUMPTION | D73: Tier 1 (developed, treated as 0). Tiers (0 / 1 / 2 / 4%) are an analyst ordering by general sovereign risk, NOT a published table; replace with a sourced CRP (e.g. Damodaran) when available. The September blended 1.5% is reproduced approximately by this scheme on the old four-country split (1.6%).
A74: Singapore | B74: 0 | C74: ILLUSTRATIVE ASSUMPTION | D74: Tier 1 (developed, treated as 0). Tiers (0 / 1 / 2 / 4%) are an analyst ordering by general sovereign risk, NOT a published table; replace with a sourced CRP (e.g. Damodaran) when available. The September blended 1.5% is reproduced approximately by this scheme on the old four-country split (1.6%).
A75: Papua New Guinea | B75: 0.04 | C75: ILLUSTRATIVE ASSUMPTION | D75: Tier 4 (highest assumed risk). Tiers (0 / 1 / 2 / 4%) are an analyst ordering by general sovereign risk, NOT a published table; replace with a sourced CRP (e.g. Damodaran) when available. The September blended 1.5% is reproduced approximately by this scheme on the old four-country split (1.6%).
A76: Revenue-weighted country risk premium | B76: =SUMPRODUCT(B49:B55,B69:B75) -> 0.0144 | C76: ANALYST CALCULATION | D76: Singapore and Australia pull it down, as intended.
A78: Sensitivity note: how much does the undisclosed country split matter?
A79: Blended tax if all seven countries were weighted equally | B79: =AVERAGE(B59:B65) -> 0.23285714 | C79: ANALYST CALCULATION | D79: Alternative split for comparison only.
A80: Country risk premium if equally weighted | B80: =AVERAGE(B69:B75) -> 0.014285714 | C80: ANALYST CALCULATION
A81: WACC change under the equal-weight split (percentage points) | B81: =(B89*(1-B79)*B91+(B84+B86*B85+B80)*(1-B91))-B92 -> -0.00022845714 | C81: ANALYST CALCULATION | D81: Difference between WACC recomputed with the equal-weight tax and CRP and the base WACC. Small: the split mainly moves tax and CRP, not revenue (revenue totals are reported).
A83: 5. Discount rate
A84: Risk-free rate | B84: 0.04 | C84: ILLUSTRATIVE ASSUMPTION | D84: Unchanged from the September model.
A85: Equity risk premium | B85: 0.055 | C85: ILLUSTRATIVE ASSUMPTION | D85: Unchanged from the September model.
A86: Beta (peer median) | B86: 0.821 | C86: ANALYST CALCULATION | D86: Median 5-year beta of the five comps with a reported beta, Yahoo Finance pull of 2026-09-18 (SRC-034). Same input as the September model; not refreshed.
A87: Country risk premium (revenue-weighted, from section 4) | B87: =B76 -> 0.0144 | C87: ANALYST CALCULATION | D87: Replaces the September flat 1.5%.
A88: Cost of equity | B88: =B84+B86*B85+B87 -> 0.099555 | C88: ANALYST CALCULATION | D88: Rf + beta x ERP + CRP.
A89: Pre-tax cost of debt | B89: 0.055 | C89: ILLUSTRATIVE ASSUMPTION | D89: Unchanged from the September model.
A90: After-tax cost of debt | B90: =B89*(1-B66) -> 0.042878 | C90: ANALYST CALCULATION | D90: Uses the blended statutory rate.
A91: Target debt / (debt + equity) | B91: 0.2 | C91: ILLUSTRATIVE ASSUMPTION | D91: Unchanged from the September model.
A92: WACC | B92: =B90*B91+B88*(1-B91) -> 0.0882196 | C92: ANALYST CALCULATION
A93: Terminal growth rate (all cases) | B93: 0.03 | C93: ILLUSTRATIVE ASSUMPTION | D93: Unchanged from the September model; held equal across cases so the cases differ only in operating drivers.
A94: Sensitivity step: WACC | B94: 0.005 | C94: ILLUSTRATIVE ASSUMPTION | D94: Grid spacing and the Low / High scenario shift.
A95: Sensitivity step: terminal growth | B95: 0.005 | C95: ILLUSTRATIVE ASSUMPTION | D95: Grid spacing and the Low / High scenario shift.
A96: Sensitivity step: terminal EBITDA margin | B96: 0.02 | C96: ILLUSTRATIVE ASSUMPTION | D96: Grid spacing for the margin x WACC table.
A98: 6. Operating assumptions common to all cases (ILLUSTRATIVE, unchanged from September unless stated)
A99: Gross margin (used only for COGS in working capital) | B99: 0.45 | C99: ILLUSTRATIVE ASSUMPTION | D99: No disclosure. EBITDA is driven directly by the case margin, so this does not affect EBITDA or value.
A100: D&A % of revenue | B100: 0.025 | C100: ILLUSTRATIVE ASSUMPTION | D100: No disclosure.
A101: Capex % of revenue — FY2026E | B101: 0.035 | C101: ILLUSTRATIVE ASSUMPTION | D101: 3.0% maintenance, 3.5% in the two separation years.
A102: Capex % of revenue — FY2027E | B102: 0.035 | C102: ILLUSTRATIVE ASSUMPTION | D102: As above.
A103: Capex % of revenue — FY2028E | B103: 0.03 | C103: ILLUSTRATIVE ASSUMPTION | D103: As above.
A104: Capex % of revenue — FY2029E | B104: 0.03 | C104: ILLUSTRATIVE ASSUMPTION | D104: As above.
A105: Capex % of revenue — FY2030E | B105: 0.03 | C105: ILLUSTRATIVE ASSUMPTION | D105: As above.
A106: Terminal-year capex % of revenue | B106: 0.03 | C106: ILLUSTRATIVE ASSUMPTION | D106: Steady-state maintenance level used in the terminal-year normalisation.
A107: Days sales outstanding | B107: 45 | C107: ILLUSTRATIVE ASSUMPTION | D107: No disclosure.
A108: Days inventory outstanding | B108: 60 | C108: ILLUSTRATIVE ASSUMPTION | D108: No disclosure.
A109: Days payable outstanding | B109: 45 | C109: ILLUSTRATIVE ASSUMPTION | D109: No disclosure.
A110: TSA cost % of revenue — FY2026E | B110: 0.03 | C110: ILLUSTRATIVE ASSUMPTION | D110: Transition-services cost shown as a COMPONENT of opex inside the case EBITDA margin (it does not reduce EBITDA a second time).
... A120: One-time separation cost, FY2026E (EUR m, pre-tax) | B120: 8 | C120: ILLUSTRATIVE ASSUMPTION | D120: Unchanged from September, although the perimeter is now seven countries across two buyers' structures (UNDER-stated if anything). Deducted from FY2026E free cash flow.

Sheet Case_Drivers
A1: Case drivers: revenue growth and EBITDA margin, FY2026E-FY2030E
A2: Three cases. The active case is chosen on Assumptions. Everything else (D&A, capex, working capital, tax, WACC, terminal growth) is common to all cases.
B4: FY2026E | C4: FY2027E | D4: FY2028E | E4: FY2029E | F4: FY2030E | G4: Classification | H4: Rationale
A5: Revenue growth
A6: Base (seller / standalone view) | B6: 0.05 | C6: 0.05 | D6: 0.05 | E6: 0.05 | F6: 0.05 | G6: ILLUSTRATIVE ASSUMPTION | H6: ~5% p.a., anchored to the ASEAN paints-and-coatings market growth of about 5.0% a year (SRC-001, ION Analytics). Applying the market rate to this business is an assumption; no cited source gives growth for the business itself.
A7: Buyer (Nippon Paint's 2026 projection, then Base growth) | B7: =(Assumptions!$B$29/Assumptions!$B$7)/Assumptions!$B$26-1 -> 0.13402062 | C7: =C6 -> 0.05 | D7: =D6 -> 0.05 | E7: =E6 -> 0.05 | F7: =F6 -> 0.05 | G7: ANALYST CALCULATION | H7: FY2026E growth is whatever takes FY2025 reported revenue to Nippon Paint's projected ~USD 330m (REPORTED, single-source, buyer's view). From FY2027E it falls back to Base growth.
A8: Downside | B8: 0.03 | C8: 0.03 | D8: 0.03 | E8: 0.03 | F8: 0.03 | G8: ILLUSTRATIVE ASSUMPTION | H8: 3% p.a.: below the ~5% market rate, consistent with share loss or weaker markets during a carve-out and integration. No source; a stress, not a forecast.
A9: ACTIVE case | B9: =CHOOSE(Assumptions!$B$35,B6,B7,B8) -> 0.05 | C9: =CHOOSE(Assumptions!$B$35,C6,C7,C8) -> 0.05 | D9: =CHOOSE(Assumptions!$B$35,D6,D7,D8) -> 0.05 | E9: =CHOOSE(Assumptions!$B$35,E6,E7,E8) -> 0.05 | F9: =CHOOSE(Assumptions!$B$35,F6,F7,F8) -> 0.05 | G9: ANALYST CALCULATION | H9: Selected on Assumptions.
A11: EBITDA margin
A12: Base: reported FY2025 margin held flat | B12: =Assumptions!$B$24 -> 0.2233677 | C12: =Assumptions!$B$24 -> 0.2233677 | D12: =Assumptions!$B$24 -> 0.2233677 | E12: =Assumptions!$B$24 -> 0.2233677 | F12: =Assumptions!$B$24 -> 0.2233677 | G12: ILLUSTRATIVE ASSUMPTION | H12: Starts at the reported FY2025 margin (~22.3%) and holds it. No expansion is assumed because no cited source supports one; this is the seller / standalone view.
A13: Buyer: 2026 projection, then fades | B13: =Assumptions!$B$30 -> 0.26 | C13: =$B$13-($B$13-Assumptions!$B$24)*(1-Case_Drivers!$B$17)*1/4 -> 0.25542096 | D13: =$B$13-($B$13-Assumptions!$B$24)*(1-Case_Drivers!$B$17)*2/4 -> 0.25084192 | E13: =$B$13-($B$13-Assumptions!$B$24)*(1-Case_Drivers!$B$17)*3/4 -> 0.24626289 | F13: =$B$13-($B$13-Assumptions!$B$24)*(1-Case_Drivers!$B$17)*4/4 -> 0.24168385 | G13: ILLUSTRATIVE ASSUMPTION | H13: FY2026E = Nippon Paint's projected ~26% (REPORTED, single-source). It then fades linearly so that, by FY2030E, only the share of the uplift set in the cell below is retained. The fade rule is an assumption; a buyer would argue for a higher persistent margin.
A14: Downside: Base less standalone step-down | B14: =B12-B18 -> 0.2133677 | C14: =C12-C18 -> 0.2033677 | D14: =D12-D18 -> 0.2033677 | E14: =E12-E18 -> 0.2033677 | F14: =F12-F18 -> 0.2033677 | G14: ILLUSTRATIVE ASSUMPTION | H14: Base margin less the step-down below. Reflects the loss of AkzoNobel group procurement scale and the cost of replacing Global Business Services, which stay with AkzoNobel (standalone cost risk).
A15: ACTIVE case | B15: =CHOOSE(Assumptions!$B$35,B12,B13,B14) -> 0.2233677 | C15: =CHOOSE(Assumptions!$B$35,C12,C13,C14) -> 0.2233677 | D15: =CHOOSE(Assumptions!$B$35,D12,D13,D14) -> 0.2233677 | E15: =CHOOSE(Assumptions!$B$35,E12,E13,E14) -> 0.2233677 | F15: =CHOOSE(Assumptions!$B$35,F12,F13,F14) -> 0.2233677 | G15: ANALYST CALCULATION | H15: Selected on Assumptions.
A16: Case parameters
A17: Share of the buyer's FY2026E margin uplift retained by FY2030E | B17: 0.5 | G17: ILLUSTRATIVE ASSUMPTION | H17: 0.5 means the margin ends midway between the buyer's 26% and the Base margin. No source; it is the single parameter that separates 'Buyer' from 'Base' after FY2026E.
A18: Downside margin step-down vs Base (percentage points) | B18: 0.01 | C18: 0.02 | D18: 0.02 | E18: 0.02 | F18: 0.02 | G18: ILLUSTRATIVE ASSUMPTION | H18: 1pp in FY2026E rising to 2pp from FY2027E. A stress input, not a forecast: it is the model's only allowance for standalone-cost risk, since TSA and stranded costs are shown inside the margin rather than deducted again.

Sheet Revenue_Build
A1: Revenue build — seven countries, active case
A2: FY2024-FY2025 are REPORTED figures (not back-solved). Forecast = prior year x (1 + active-case growth). Country split is ILLUSTRATIVE.
A4: EUR m unless stated | B4: FY2024 | C4: FY2025 | D4: FY2026E | E4: FY2027E | F4: FY2028E | G4: FY2029E | H4: FY2030E
A5: Revenue (USD m) | B5: =Assumptions!$B$19 -> 299 | C5: =Assumptions!$B$20 -> 291 | D5: =D6*Assumptions!$B$7 -> 305.55 | E5: =E6*Assumptions!$B$7 -> 320.8275 | F5: =F6*Assumptions!$B$7 -> 336.86888 | G5: =G6*Assumptions!$B$7 -> 353.71232 | H5: =H6*Assumptions!$B$7 -> 371.39793
A6: Revenue (EUR m) | B6: =B5/Assumptions!$B$7 -> 265.77778 | C6: =C5/Assumptions!$B$7 -> 258.66667 | D6: =C6*(1+Case_Drivers!$B$9) -> 271.6 | E6: =D6*(1+Case_Drivers!$C$9) -> 285.18 | F6: =E6*(1+Case_Drivers!$D$9) -> 299.439 | G6: =F6*(1+Case_Drivers!$E$9) -> 314.41095 | H6: =G6*(1+Case_Drivers!$F$9) -> 330.1315
A7: Growth % YoY | C7: =C6/B6-1 -> -0.026755853 | D7: =D6/C6-1 -> 0.05 | E7: =E6/D6-1 -> 0.05 | F7: =F6/E6-1 -> 0.05 | G7: =G6/F6-1 -> 0.05 | H7: =H6/G6-1 -> 0.05
A8: FY2024-FY2025: REPORTED, corroborated (see Assumptions section 2). FY2026E+: ANALYST CALCULATION on ILLUSTRATIVE growth.
A9: Revenue by country (EUR m) — ILLUSTRATIVE split
A10: Indonesia | B10: =B$6*Assumptions!$B$49 -> 90.364444 | C10: =C$6*Assumptions!$B$49 -> 87.946667 | D10: =D$6*Assumptions!$B$49 -> 92.344 | E10: =E$6*Assumptions!$B$49 -> 96.9612 | F10: =F$6*Assumptions!$B$49 -> 101.80926 | G10: =G$6*Assumptions!$B$49 -> 106.89972 | H10: =H$6*Assumptions!$B$49 -> 112.24471
A11: Thailand | B11: =B$6*Assumptions!$B$50 -> 56.477778 | C11: =C$6*Assumptions!$B$50 -> 54.966667 | D11: =D$6*Assumptions!$B$50 -> 57.715 | E11: =E$6*Assumptions!$B$50 -> 60.60075 | F11: =F$6*Assumptions!$B$50 -> 63.630787 | G11: =G$6*Assumptions!$B$50 -> 66.812327 | H11: =H$6*Assumptions!$B$50 -> 70.152943
A12: Vietnam | B12: =B$6*Assumptions!$B$51 -> 45.182222 | C12: =C$6*Assumptions!$B$51 -> 43.973333 | D12: =D$6*Assumptions!$B$51 -> 46.172 | E12: =E$6*Assumptions!$B$51 -> 48.4806 | F12: =F$6*Assumptions!$B$51 -> 50.90463 | G12: =G$6*Assumptions!$B$51 -> 53.449861 | H12: =H$6*Assumptions!$B$51 -> 56.122355
A13: Malaysia | B13: =B$6*Assumptions!$B$52 -> 33.886667 | C13: =C$6*Assumptions!$B$52 -> 32.98 | D13: =D$6*Assumptions!$B$52 -> 34.629 | E13: =E$6*Assumptions!$B$52 -> 36.36045 | F13: =F$6*Assumptions!$B$52 -> 38.178472 | G13: =G$6*Assumptions!$B$52 -> 40.087396 | H13: =H$6*Assumptions!$B$52 -> 42.091766
A14: Australia | B14: =B$6*Assumptions!$B$53 -> 21.262222 | C14: =C$6*Assumptions!$B$53 -> 20.693333 | D14: =D$6*Assumptions!$B$53 -> 21.728 | E14: =E$6*Assumptions!$B$53 -> 22.8144 | F14: =F$6*Assumptions!$B$53 -> 23.95512 | G14: =G$6*Assumptions!$B$53 -> 25.152876 | H14: =H$6*Assumptions!$B$53 -> 26.41052
A15: Singapore | B15: =B$6*Assumptions!$B$54 -> 13.288889 | C15: =C$6*Assumptions!$B$54 -> 12.933333 | D15: =D$6*Assumptions!$B$54 -> 13.58 | E15: =E$6*Assumptions!$B$54 -> 14.259 | F15: =F$6*Assumptions!$B$54 -> 14.97195 | G15: =G$6*Assumptions!$B$54 -> 15.720548 | H15: =H$6*Assumptions!$B$54 -> 16.506575
A16: Papua New Guinea | B16: =B$6*Assumptions!$B$55 -> 5.3155556 | C16: =C$6*Assumptions!$B$55 -> 5.1733333 | D16: =D$6*Assumptions!$B$55 -> 5.432 | E16: =E$6*Assumptions!$B$55 -> 5.7036 | F16: =F$6*Assumptions!$B$55 -> 5.98878 | G16: =G$6*Assumptions!$B$55 -> 6.288219 | H16: =H$6*Assumptions!$B$55 -> 6.6026299
A17: Check: countries sum to total | B17: =SUM(B10:B16)-B6 -> 0 | C17: =SUM(C10:C16)-C6 -> 0 | D17: =SUM(D10:D16)-D6 -> 0 | E17: =SUM(E10:E16)-E6 -> 0 | F17: =SUM(F10:F16)-F6 -> 0 | G17: =SUM(G10:G16)-G6 -> 0 | H17: =SUM(H10:H16)-H6 -> 0

Sheet Working_Capital
A1: Working capital schedule — active case
A2: ILLUSTRATIVE day-count assumptions applied to REPORTED FY2024-FY2025 revenue and forecast revenue. No balance-sheet data is disclosed.
A4: EUR m | B4: FY2024 | C4: FY2025 | D4: FY2026E | E4: FY2027E | F4: FY2028E | G4: FY2029E | H4: FY2030E
A5: Revenue | B5: =Revenue_Build!B6 -> 265.77778 | C5: =Revenue_Build!C6 -> 258.66667 | D5: =Revenue_Build!D6 -> 271.6 | E5: =Revenue_Build!E6 -> 285.18 | F5: =Revenue_Build!F6 -> 299.439 | G5: =Revenue_Build!G6 -> 314.41095 | H5: =Revenue_Build!H6 -> 330.1315
A6: COGS = revenue x (1 - gross margin) | B6: =B5*(1-Assumptions!$B$99) -> 146.17778 | C6: =C5*(1-Assumptions!$B$99) -> 142.26667 | D6: =D5*(1-Assumptions!$B$99) -> 149.38 | E6: =E5*(1-Assumptions!$B$99) -> 156.849 | F6: =F5*(1-Assumptions!$B$99) -> 164.69145 | G6: =G5*(1-Assumptions!$B$99) -> 172.92602 | H6: =H5*(1-Assumptions!$B$99) -> 181.57232
A8: Accounts receivable | B8: =B5*Assumptions!$B$107/365 -> 32.767123 | C8: =C5*Assumptions!$B$107/365 -> 31.890411 | D8: =D5*Assumptions!$B$107/365 -> 33.484932 | E8: =E5*Assumptions!$B$107/365 -> 35.159178 | F8: =F5*Assumptions!$B$107/365 -> 36.917137 | G8: =G5*Assumptions!$B$107/365 -> 38.762994 | H8: =H5*Assumptions!$B$107/365 -> 40.701144
A9: Inventory | B9: =B6*Assumptions!$B$108/365 -> 24.029224 | C9: =C6*Assumptions!$B$108/365 -> 23.386301 | D9: =D6*Assumptions!$B$108/365 -> 24.555616 | E9: =E6*Assumptions!$B$108/365 -> 25.783397 | F9: =F6*Assumptions!$B$108/365 -> 27.072567 | G9: =G6*Assumptions!$B$108/365 -> 28.426195 | H9: =H6*Assumptions!$B$108/365 -> 29.847505
A10: Accounts payable | B10: =-B6*Assumptions!$B$109/365 -> -18.021918 | C10: =-C6*Assumptions!$B$109/365 -> -17.539726 | D10: =-D6*Assumptions!$B$109/365 -> -18.416712 | E10: =-E6*Assumptions!$B$109/365 -> -19.337548 | F10: =-F6*Assumptions!$B$109/365 -> -20.304425 | G10: =-G6*Assumptions!$B$109/365 -> -21.319647 | H10: =-H6*Assumptions!$B$109/365 -> -22.385629
A12: Net working capital | B12: =B8+B9+B10 -> 38.774429 | C12: =C8+C9+C10 -> 37.736986 | D12: =D8+D9+D10 -> 39.623836 | E12: =E8+E9+E10 -> 41.605027 | F12: =F8+F9+F10 -> 43.685279 | G12: =G8+G9+G10 -> 45.869543 | H12: =H8+H9+H10 -> 48.16302
A13: NWC / revenue | B13: =B12/B5 -> 0.14589041 | C13: =C12/C5 -> 0.14589041 | D13: =D12/D5 -> 0.14589041 | E13: =E12/E5 -> 0.14589041 | F13: =F12/F5 -> 0.14589041 | G13: =G12/G5 -> 0.14589041 | H13: =H12/H5 -> 0.14589041
A14: Change in NWC (increase = cash outflow) | C14: =C12-B12 -> -1.0374429 | D14: =D12-C12 -> 1.8868493 | E14: =E12-D12 -> 1.9811918 | F14: =F12-E12 -> 2.0802514 | G14: =G12-F12 -> 2.1842639 | H14: =H12-G12 -> 2.2934771
A16: Steady-state NWC / revenue (used by the Cases sheet and terminal year) | B16: =(Assumptions!$B$107+(1-Assumptions!$B$99)*(Assumptions!$B$108-Assumptions!$B$109))/365 -> 0.14589041

Sheet Capex_DA
A1: Capex and D&A — active case
A2: ILLUSTRATIVE % of revenue; forecast years only (history is not disclosed).
A4: EUR m | B4: FY2024 | C4: FY2025 | D4: FY2026E | E4: FY2027E | F4: FY2028E | G4: FY2029E | H4: FY2030E
A5: Revenue | B5: =Revenue_Build!B6 -> 265.77778 | C5: =Revenue_Build!C6 -> 258.66667 | D5: =Revenue_Build!D6 -> 271.6 | E5: =Revenue_Build!E6 -> 285.18 | F5: =Revenue_Build!F6 -> 299.439 | G5: =Revenue_Build!G6 -> 314.41095 | H5: =Revenue_Build!H6 -> 330.1315
A7: Capex | D7: =D5*Assumptions!$B$101 -> 9.506 | E7: =E5*Assumptions!$B$102 -> 9.9813 | F7: =F5*Assumptions!$B$103 -> 8.98317 | G7: =G5*Assumptions!$B$104 -> 9.4323285 | H7: =H5*Assumptions!$B$105 -> 9.9039449
A8: Capex % of revenue | D8: =D7/D5 -> 0.035 | E8: =E7/E5 -> 0.035 | F8: =F7/F5 -> 0.03 | G8: =G7/G5 -> 0.03 | H8: =H7/H5 -> 0.03
A10: D&A | D10: =D5*Assumptions!$B$100 -> 6.79 | E10: =E5*Assumptions!$B$100 -> 7.1295 | F10: =F5*Assumptions!$B$100 -> 7.485975 | G10: =G5*Assumptions!$B$100 -> 7.8602738 | H10: =H5*Assumptions!$B$100 -> 8.2532874
A11: D&A % of revenue | D11: =D10/D5 -> 0.025 | E11: =E10/E5 -> 0.025 | F11: =F10/F5 -> 0.025 | G11: =G10/G5 -> 0.025 | H11: =H10/H5 -> 0.025

Sheet Carveout_PnL
A1: Carve-out P&L and unlevered free cash flow — active case
A2: ="Active case: "&Assumptions!$B$36&". FY2024-FY2025 EBITDA are REPORTED; FY2026E+ are ANALYST CALCULATIONS on ILLUSTRATIVE case drivers." -> Active case: Base. FY2024-FY2025 EBITDA are REPORTED; FY2026E+ are ANALYST CALCULATIONS on ILLUSTRATIVE case drivers.
A4: EUR m | B4: FY2024 | C4: FY2025 | D4: FY2026E | E4: FY2027E | F4: FY2028E | G4: FY2029E | H4: FY2030E
A5: Revenue | B5: =Revenue_Build!B6 -> 265.77778 | C5: =Revenue_Build!C6 -> 258.66667 | D5: =Revenue_Build!D6 -> 271.6 | E5: =Revenue_Build!E6 -> 285.18 | F5: =Revenue_Build!F6 -> 299.439 | G5: =Revenue_Build!G6 -> 314.41095 | H5: =Revenue_Build!H6 -> 330.1315
A6: Revenue growth % YoY | C6: =C5/B5-1 -> -0.026755853 | D6: =D5/C5-1 -> 0.05 | E6: =E5/D5-1 -> 0.05 | F6: =F5/E5-1 -> 0.05 | G6: =G5/F5-1 -> 0.05 | H6: =H5/G5-1 -> 0.05
A8: Gross profit (illustrative gross margin) | D8: =D5*Assumptions!$B$99 -> 122.22 | E8: =E5*Assumptions!$B$99 -> 128.331 | F8: =F5*Assumptions!$B$99 -> 134.74755 | G8: =G5*Assumptions!$B$99 -> 141.48493 | H8: =H5*Assumptions!$B$99 -> 148.55917
A10: EBITDA | B10: =Assumptions!$B$27 -> 61.333333 | C10: =Assumptions!$B$28 -> 57.777778 | D10: =D5*Case_Drivers!$B$15 -> 60.666667 | E10: =E5*Case_Drivers!$C$15 -> 63.7 | F10: =F5*Case_Drivers!$D$15 -> 66.885 | G10: =G5*Case_Drivers!$E$15 -> 70.22925 | H10: =H5*Case_Drivers!$F$15 -> 73.740713
A11: EBITDA margin % | B11: =B10/B5 -> 0.23076923 | C11: =C10/C5 -> 0.2233677 | D11: =D10/D5 -> 0.2233677 | E11: =E10/E5 -> 0.2233677 | F11: =F10/F5 -> 0.2233677 | G11: =G10/G5 -> 0.2233677 | H11: =H10/H5 -> 0.2233677
A13: Operating-cost bridge (components inside the case margin, not extra deductions):
A14: TSA costs | D14: =-D5*Assumptions!$B$110 -> -8.148 | E14: =-E5*Assumptions!$B$111 -> -4.2777 | F14: =-F5*Assumptions!$B$112 -> 0 | G14: =-G5*Assumptions!$B$113 -> 0 | H14: =-H5*Assumptions!$B$114 -> 0
A15: Stranded / standalone replacement costs | D15: =-D5*Assumptions!$B$115 -> -2.716 | E15: =-E5*Assumptions!$B$116 -> -2.8518 | F15: =-F5*Assumptions!$B$117 -> 0 | G15: =-G5*Assumptions!$B$118 -> 0 | H15: =-H5*Assumptions!$B$119 -> 0
A16: Standalone operating expenses (plug: gross profit less EBITDA less the two lines above) | D16: =-(D8-D10+D14+D15) -> -50.689333 | E16: =-(E8-E10+E14+E15) -> -57.5015 | F16: =-(F8-F10+F14+F15) -> -67.86255 | G16: =-(G8-G10+G14+G15) -> -71.255678 | H16: =-(H8-H10+H14+H15) -> -74.818461
A17: Check: gross profit + bridge = EBITDA | D17: =D8+D14+D15+D16-D10 -> 0 | E17: =E8+E14+E15+E16-E10 -> 0 | F17: =F8+F14+F15+F16-F10 -> 0 | G17: =G8+G14+G15+G16-G10 -> 0 | H17: =H8+H14+H15+H16-H10 -> 0
A19: D&A | D19: =-Capex_DA!D10 -> -6.79 | E19: =-Capex_DA!E10 -> -7.1295 | F19: =-Capex_DA!F10 -> -7.485975 | G19: =-Capex_DA!G10 -> -7.8602738 | H19: =-Capex_DA!H10 -> -8.2532874
A20: EBIT | D20: =D10+D19 -> 53.876667 | E20: =E10+E19 -> 56.5705 | F20: =F10+F19 -> 59.399025 | G20: =G10+G19 -> 62.368976 | H20: =H10+H19 -> 65.487425
A22: Cash taxes (EBIT x blended statutory rate) | D22: =-MAX(D20,0)*Assumptions!$B$66 -> -11.874417 | E22: =-MAX(E20,0)*Assumptions!$B$66 -> -12.468138 | F22: =-MAX(F20,0)*Assumptions!$B$66 -> -13.091545 | G22: =-MAX(G20,0)*Assumptions!$B$66 -> -13.746122 | H22: =-MAX(H20,0)*Assumptions!$B$66 -> -14.433428
A23: Capex | D23: =-Capex_DA!D7 -> -9.506 | E23: =-Capex_DA!E7 -> -9.9813 | F23: =-Capex_DA!F7 -> -8.98317 | G23: =-Capex_DA!G7 -> -9.4323285 | H23: =-Capex_DA!H7 -> -9.9039449
A24: Change in NWC (increase = outflow) | D24: =-Working_Capital!D14 -> -1.8868493 | E24: =-Working_Capital!E14 -> -1.9811918 | F24: =-Working_Capital!F14 -> -2.0802514 | G24: =-Working_Capital!G14 -> -2.1842639 | H24: =-Working_Capital!H14 -> -2.2934771
A25: One-time separation costs (pre-tax) | D25: =-Assumptions!$B$120 -> -8 | E25: 0 | F25: 0 | G25: 0 | H25: 0
A27: Unlevered free cash flow | D27: =D10+D22+D23+D24+D25 -> 29.3994 | E27: =E10+E22+E23+E24+E25 -> 39.26937 | F27: =F10+F22+F23+F24+F25 -> 42.730034 | G27: =G10+G22+G23+G24+G25 -> 44.866535 | H27: =H10+H22+H23+H24+H25 -> 47.109862
A29: UFCF = EBITDA - cash taxes - capex - change in NWC - separation costs (equivalent to EBIT - tax + D&A - capex - dNWC - separation).

Sheet DCF_Valuation
A1: DCF valuation — active case
A2: ="Active case: "&Assumptions!$B$36&". Terminal value uses a normalised terminal year (margin, D&A, capex and NWC at steady state), so the margin and growth sensitivities are exact." -> Active case: Base. Terminal value uses a normalised terminal year (margin, D&A, capex and NWC at steady state), so the margin and growth sensitivities are exact.
A4: EUR m | B4: FY2026E | C4: FY2027E | D4: FY2028E | E4: FY2029E | F4: FY2030E
A5: Unlevered free cash flow | B5: =Carveout_PnL!D27 -> 29.3994 | C5: =Carveout_PnL!E27 -> 39.26937 | D5: =Carveout_PnL!F27 -> 42.730034 | E5: =Carveout_PnL!G27 -> 44.866535 | F5: =Carveout_PnL!H27 -> 47.109862
A6: Period (t) | B6: 1 | C6: 2 | D6: 3 | E6: 4 | F6: 5
A7: Discount factor at WACC | B7: =1/(1+Assumptions!$B$92)^B6 -> 0.91893217 | C7: =1/(1+Assumptions!$B$92)^C6 -> 0.84443634 | D7: =1/(1+Assumptions!$B$92)^D6 -> 0.77597972 | E7: =1/(1+Assumptions!$B$92)^E6 -> 0.71307272 | F7: =1/(1+Assumptions!$B$92)^F6 -> 0.65526547
A8: PV of FCF | B8: =B5*B7 -> 27.016054 | C8: =C5*C7 -> 33.160483 | D8: =D5*D7 -> 33.157639 | E8: =E5*E7 -> 31.993103 | F8: =F5*F7 -> 30.869466
A10: Terminal year (normalised)
A11: FY2030E revenue | B11: =Carveout_PnL!H5 -> 330.1315
A12: Terminal EBITDA margin (default = FY2030E case margin; overwrite to test) | B12: =Carveout_PnL!H11 -> 0.2233677
A13: D&A % of revenue | B13: =Assumptions!$B$100 -> 0.025
A14: Terminal capex % of revenue | B14: =Assumptions!$B$106 -> 0.03
A15: Blended statutory tax rate | B15: =Assumptions!$B$66 -> 0.2204
A16: Steady-state NWC / revenue | B16: =Working_Capital!$B$16 -> 0.14589041
A17: Terminal growth | B17: =Assumptions!$B$93 -> 0.03
A18: WACC | B18: =Assumptions!$B$92 -> 0.0882196
A19: A = free cash flow per EUR of revenue = (m - D&A)(1 - t) + D&A - capex | B19: =(B12-B13)*(1-B15)+B13-B14 -> 0.14964746
A20: Terminal-year free cash flow = FY2030E revenue x ((1 + g) x A - g x NWC%) | B20: =B11*((1+B17)*B19-B17*B16) -> 49.440549
A21: Terminal value = terminal FCF / (WACC - g) | B21: =B20/(B18-B17) -> 849.20798
A22: PV of terminal value | B22: =B21*F7 -> 556.45666
A23: Sum of PV of FCF, FY2026E-FY2030E | B23: =SUM(B8:F8) -> 156.19674
A24: ENTERPRISE VALUE (EUR m) | B24: =B22+B23 -> 712.65341
A25: TV as % of enterprise value | B25: =B22/B24 -> 0.78082369
A26: Implied EV / FY2025 reported EBITDA | B26: =B24/Assumptions!$B$28 -> 12.334386
A27: Implied EV / FY2026E EBITDA (active case) | B27: =B24/Carveout_PnL!D10 -> 11.747034
A28: Implied EV / FY2025 reported revenue | B28: =B24/Assumptions!$B$26 -> 2.7551034
A29: Implied terminal EV / FY2030E EBITDA | B29: =B21/Carveout_PnL!H10 -> 11.516135
A31: Sensitivity (a): enterprise value by WACC x terminal growth (EUR m)
A32: WACC down, terminal growth across
A33: WACC \ g | B33: =$B$17+(-2)*Assumptions!$B$95 -> 0.02 | C33: =$B$17+(-1)*Assumptions!$B$95 -> 0.025 | D33: =$B$17+(0)*Assumptions!$B$95 -> 0.03 | E33: =$B$17+(1)*Assumptions!$B$95 -> 0.035 | F33: =$B$17+(2)*Assumptions!$B$95 -> 0.04
A34: =$B$18+(-2)*Assumptions!$B$94 -> 0.0782196 | B34: =B$5/(1+$A34)^1+C$5/(1+$A34)^2+D$5/(1+$A34)^3+E$5/(1+$A34)^4+F$5/(1+$A34)^5+$B$11*((1+B$33)*(($B$12-$B$13)*(1-$B$15)+$B$13-$B$14)-B$33*$B$16)/($A34-B$33)/(1+$A34)^5 -> 743.25621 | C34: =B$5/(1+$A34)^1+C$5/(1+$A34)^2+D$5/(1+$A34)^3+E$5/(1+$A34)^4+F$5/(1+$A34)^5+$B$11*((1+C$33)*(($B$12-$B$13)*(1-$B$15)+$B$13-$B$14)-C$33*$B$16)/($A34-C$33)/(1+$A34)^5 -> 798.07146 | D34: =B$5/(1+$A34)^1+C$5/(1+$A34)^2+D$5/(1+$A34)^3+E$5/(1+$A34)^4+F$5/(1+$A34)^5+$B$11*((1+D$33)*(($B$12-$B$13)*(1-$B$15)+$B$13-$B$14)-D$33*$B$16)/($A34-D$33)/(1+$A34)^5 -> 864.25454 | E34: =B$5/(1+$A34)^1+C$5/(1+$A34)^2+D$5/(1+$A34)^3+E$5/(1+$A34)^4+F$5/(1+$A34)^5+$B$11*((1+E$33)*(($B$12-$B$13)*(1-$B$15)+$B$13-$B$14)-E$33*$B$16)/($A34-E$33)/(1+$A34)^5 -> 945.75084 | F34: =B$5/(1+$A34)^1+C$5/(1+$A34)^2+D$5/(1+$A34)^3+E$5/(1+$A34)^4+F$5/(1+$A34)^5+$B$11*((1+F$33)*(($B$12-$B$13)*(1-$B$15)+$B$13-$B$14)-F$33*$B$16)/($A34-F$33)/(1+$A34)^5 -> 1048.5703
A35: =$B$18+(-1)*Assumptions!$B$94 -> 0.0832196 | B35: =B$5/(1+$A35)^1+C$5/(1+$A35)^2+D$5/(1+$A35)^3+E$5/(1+$A35)^4+F$5/(1+$A35)^5+$B$11*((1+B$33)*(($B$12-$B$13)*(1-$B$15)+$B$13-$B$14)-B$33*$B$16)/($A35-B$33)/(1+$A35)^5 -> 682.65533 | C35: =B$5/(1+$A35)^1+C$5/(1+$A35)^2+D$5/(1+$A35)^3+E$5/(1+$A35)^4+F$5/(1+$A35)^5+$B$11*((1+C$33)*(($B$12-$B$13)*(1-$B$15)+$B$13-$B$14)-C$33*$B$16)/($A35-C$33)/(1+$A35)^5 -> 727.75042 | D35: =B$5/(1+$A35)^1+C$5/(1+$A35)^2+D$5/(1+$A35)^3+E$5/(1+$A35)^4+F$5/(1+$A35)^5+$B$11*((1+D$33)*(($B$12-$B$13)*(1-$B$15)+$B$13-$B$14)-D$33*$B$16)/($A35-D$33)/(1+$A35)^5 -> 781.31891 | E35: =B$5/(1+$A35)^1+C$5/(1+$A35)^2+D$5/(1+$A35)^3+E$5/(1+$A35)^4+F$5/(1+$A35)^5+$B$11*((1+E$33)*(($B$12-$B$13)*(1-$B$15)+$B$13-$B$14)-E$33*$B$16)/($A35-E$33)/(1+$A35)^5 -> 845.99667 | F35: =B$5/(1+$A35)^1+C$5/(1+$A35)^2+D$5/(1+$A35)^3+E$5/(1+$A35)^4+F$5/(1+$A35)^5+$B$11*((1+F$33)*(($B$12-$B$13)*(1-$B$15)+$B$13-$B$14)-F$33*$B$16)/($A35-F$33)/(1+$A35)^5 -> 925.63934
A36: =$B$18+(0)*Assumptions!$B$94 -> 0.0882196 | B36: =B$5/(1+$A36)^1+C$5/(1+$A36)^2+D$5/(1+$A36)^3+E$5/(1+$A36)^4+F$5/(1+$A36)^5+$B$11*((1+B$33)*(($B$12-$B$13)*(1-$B$15)+$B$13-$B$14)-B$33*$B$16)/($A36-B$33)/(1+$A36)^5 -> 630.96583 | C36: =B$5/(1+$A36)^1+C$5/(1+$A36)^2+D$5/(1+$A36)^3+E$5/(1+$A36)^4+F$5/(1+$A36)^5+$B$11*((1+C$33)*(($B$12-$B$13)*(1-$B$15)+$B$13-$B$14)-C$33*$B$16)/($A36-C$33)/(1+$A36)^5 -> 668.57931 | D36: =B$5/(1+$A36)^1+C$5/(1+$A36)^2+D$5/(1+$A36)^3+E$5/(1+$A36)^4+F$5/(1+$A36)^5+$B$11*((1+D$33)*(($B$12-$B$13)*(1-$B$15)+$B$13-$B$14)-D$33*$B$16)/($A36-D$33)/(1+$A36)^5 -> 712.65341 | E36: =B$5/(1+$A36)^1+C$5/(1+$A36)^2+D$5/(1+$A36)^3+E$5/(1+$A36)^4+F$5/(1+$A36)^5+$B$11*((1+E$33)*(($B$12-$B$13)*(1-$B$15)+$B$13-$B$14)-E$33*$B$16)/($A36-E$33)/(1+$A36)^5 -> 765.00906 | F36: =B$5/(1+$A36)^1+C$5/(1+$A36)^2+D$5/(1+$A36)^3+E$5/(1+$A36)^4+F$5/(1+$A36)^5+$B$11*((1+F$33)*(($B$12-$B$13)*(1-$B$15)+$B$13-$B$14)-F$33*$B$16)/($A36-F$33)/(1+$A36)^5 -> 828.22247
A37: =$B$18+(1)*Assumptions!$B$94 -> 0.0932196 | B37: =B$5/(1+$A37)^1+C$5/(1+$A37)^2+D$5/(1+$A37)^3+E$5/(1+$A37)^4+F$5/(1+$A37)^5+$B$11*((1+B$33)*(($B$12-$B$13)*(1-$B$15)+$B$13-$B$14)-B$33*$B$16)/($A37-B$33)/(1+$A37)^5 -> 586.36144 | C37: =B$5/(1+$A37)^1+C$5/(1+$A37)^2+D$5/(1+$A37)^3+E$5/(1+$A37)^4+F$5/(1+$A37)^5+$B$11*((1+C$33)*(($B$12-$B$13)*(1-$B$15)+$B$13-$B$14)-C$33*$B$16)/($A37-C$33)/(1+$A37)^5 -> 618.1059 | D37: =B$5/(1+$A37)^1+C$5/(1+$A37)^2+D$5/(1+$A37)^3+E$5/(1+$A37)^4+F$5/(1+$A37)^5+$B$11*((1+D$33)*(($B$12-$B$13)*(1-$B$15)+$B$13-$B$14)-D$33*$B$16)/($A37-D$33)/(1+$A37)^5 -> 654.87166 | E37: =B$5/(1+$A37)^1+C$5/(1+$A37)^2+D$5/(1+$A37)^3+E$5/(1+$A37)^4+F$5/(1+$A37)^5+$B$11*((1+E$33)*(($B$12-$B$13)*(1-$B$15)+$B$13-$B$14)-E$33*$B$16)/($A37-E$33)/(1+$A37)^5 -> 697.95244 | F37: =B$5/(1+$A37)^1+C$5/(1+$A37)^2+D$5/(1+$A37)^3+E$5/(1+$A37)^4+F$5/(1+$A37)^5+$B$11*((1+F$33)*(($B$12-$B$13)*(1-$B$15)+$B$13-$B$14)-F$33*$B$16)/($A37-F$33)/(1+$A37)^5 -> 749.12812
A38: =$B$18+(2)*Assumptions!$B$94 -> 0.0982196 | B38: =B$5/(1+$A38)^1+C$5/(1+$A38)^2+D$5/(1+$A38)^3+E$5/(1+$A38)^4+F$5/(1+$A38)^5+$B$11*((1+B$33)*(($B$12-$B$13)*(1-$B$15)+$B$13-$B$14)-B$33*$B$16)/($A38-B$33)/(1+$A38)^5 -> 547.48291 | C38: =B$5/(1+$A38)^1+C$5/(1+$A38)^2+D$5/(1+$A38)^3+E$5/(1+$A38)^4+F$5/(1+$A38)^5+$B$11*((1+C$33)*(($B$12-$B$13)*(1-$B$15)+$B$13-$B$14)-C$33*$B$16)/($A38-C$33)/(1+$A38)^5 -> 574.54784 | D38: =B$5/(1+$A38)^1+C$5/(1+$A38)^2+D$5/(1+$A38)^3+E$5/(1+$A38)^4+F$5/(1+$A38)^5+$B$11*((1+D$33)*(($B$12-$B$13)*(1-$B$15)+$B$13-$B$14)-D$33*$B$16)/($A38-D$33)/(1+$A38)^5 -> 605.58011 | E38: =B$5/(1+$A38)^1+C$5/(1+$A38)^2+D$5/(1+$A38)^3+E$5/(1+$A38)^4+F$5/(1+$A38)^5+$B$11*((1+E$33)*(($B$12-$B$13)*(1-$B$15)+$B$13-$B$14)-E$33*$B$16)/($A38-E$33)/(1+$A38)^5 -> 641.52101 | F38: =B$5/(1+$A38)^1+C$5/(1+$A38)^2+D$5/(1+$A38)^3+E$5/(1+$A38)^4+F$5/(1+$A38)^5+$B$11*((1+F$33)*(($B$12-$B$13)*(1-$B$15)+$B$13-$B$14)-F$33*$B$16)/($A38-F$33)/(1+$A38)^5 -> 683.63526
A41: Sensitivity (b): enterprise value by terminal EBITDA margin x WACC (EUR m)
A42: WACC \ terminal margin | B42: =$B$12+(-2)*Assumptions!$B$96 -> 0.1833677 | C42: =$B$12+(-1)*Assumptions!$B$96 -> 0.2033677 | D42: =$B$12+(0)*Assumptions!$B$96 -> 0.2233677 | E42: =$B$12+(1)*Assumptions!$B$96 -> 0.2433677 | F42: =$B$12+(2)*Assumptions!$B$96 -> 0.2633677
A43: =$B$18+(-2)*Assumptions!$B$94 -> 0.0782196 | B43: =B$5/(1+$A43)^1+C$5/(1+$A43)^2+D$5/(1+$A43)^3+E$5/(1+$A43)^4+F$5/(1+$A43)^5+$B$11*((1+$B$17)*((B$42-$B$13)*(1-$B$15)+$B$13-$B$14)-$B$17*$B$16)/($A43-$B$17)/(1+$A43)^5 -> 713.35209 | C43: =B$5/(1+$A43)^1+C$5/(1+$A43)^2+D$5/(1+$A43)^3+E$5/(1+$A43)^4+F$5/(1+$A43)^5+$B$11*((1+$B$17)*((C$42-$B$13)*(1-$B$15)+$B$13-$B$14)-$B$17*$B$16)/($A43-$B$17)/(1+$A43)^5 -> 788.80332 | D43: =B$5/(1+$A43)^1+C$5/(1+$A43)^2+D$5/(1+$A43)^3+E$5/(1+$A43)^4+F$5/(1+$A43)^5+$B$11*((1+$B$17)*((D$42-$B$13)*(1-$B$15)+$B$13-$B$14)-$B$17*$B$16)/($A43-$B$17)/(1+$A43)^5 -> 864.25454 | E43: =B$5/(1+$A43)^1+C$5/(1+$A43)^2+D$5/(1+$A43)^3+E$5/(1+$A43)^4+F$5/(1+$A43)^5+$B$11*((1+$B$17)*((E$42-$B$13)*(1-$B$15)+$B$13-$B$14)-$B$17*$B$16)/($A43-$B$17)/(1+$A43)^5 -> 939.70577 | F43: =B$5/(1+$A43)^1+C$5/(1+$A43)^2+D$5/(1+$A43)^3+E$5/(1+$A43)^4+F$5/(1+$A43)^5+$B$11*((1+$B$17)*((F$42-$B$13)*(1-$B$15)+$B$13-$B$14)-$B$17*$B$16)/($A43-$B$17)/(1+$A43)^5 -> 1015.157
A44: =$B$18+(-1)*Assumptions!$B$94 -> 0.0832196 | B44: =B$5/(1+$A44)^1+C$5/(1+$A44)^2+D$5/(1+$A44)^3+E$5/(1+$A44)^4+F$5/(1+$A44)^5+$B$11*((1+$B$17)*((B$42-$B$13)*(1-$B$15)+$B$13-$B$14)-$B$17*$B$16)/($A44-$B$17)/(1+$A44)^5 -> 647.72032 | C44: =B$5/(1+$A44)^1+C$5/(1+$A44)^2+D$5/(1+$A44)^3+E$5/(1+$A44)^4+F$5/(1+$A44)^5+$B$11*((1+$B$17)*((C$42-$B$13)*(1-$B$15)+$B$13-$B$14)-$B$17*$B$16)/($A44-$B$17)/(1+$A44)^5 -> 714.51961 | D44: =B$5/(1+$A44)^1+C$5/(1+$A44)^2+D$5/(1+$A44)^3+E$5/(1+$A44)^4+F$5/(1+$A44)^5+$B$11*((1+$B$17)*((D$42-$B$13)*(1-$B$15)+$B$13-$B$14)-$B$17*$B$16)/($A44-$B$17)/(1+$A44)^5 -> 781.31891 | E44: =B$5/(1+$A44)^1+C$5/(1+$A44)^2+D$5/(1+$A44)^3+E$5/(1+$A44)^4+F$5/(1+$A44)^5+$B$11*((1+$B$17)*((E$42-$B$13)*(1-$B$15)+$B$13-$B$14)-$B$17*$B$16)/($A44-$B$17)/(1+$A44)^5 -> 848.1182 | F44: =B$5/(1+$A44)^1+C$5/(1+$A44)^2+D$5/(1+$A44)^3+E$5/(1+$A44)^4+F$5/(1+$A44)^5+$B$11*((1+$B$17)*((F$42-$B$13)*(1-$B$15)+$B$13-$B$14)-$B$17*$B$16)/($A44-$B$17)/(1+$A44)^5 -> 914.91749
A45: =$B$18+(0)*Assumptions!$B$94 -> 0.0882196 | B45: =B$5/(1+$A45)^1+C$5/(1+$A45)^2+D$5/(1+$A45)^3+E$5/(1+$A45)^4+F$5/(1+$A45)^5+$B$11*((1+$B$17)*((B$42-$B$13)*(1-$B$15)+$B$13-$B$14)-$B$17*$B$16)/($A45-$B$17)/(1+$A45)^5 -> 593.30845 | C45: =B$5/(1+$A45)^1+C$5/(1+$A45)^2+D$5/(1+$A45)^3+E$5/(1+$A45)^4+F$5/(1+$A45)^5+$B$11*((1+$B$17)*((C$42-$B$13)*(1-$B$15)+$B$13-$B$14)-$B$17*$B$16)/($A45-$B$17)/(1+$A45)^5 -> 652.98093 | D45: =B$5/(1+$A45)^1+C$5/(1+$A45)^2+D$5/(1+$A45)^3+E$5/(1+$A45)^4+F$5/(1+$A45)^5+$B$11*((1+$B$17)*((D$42-$B$13)*(1-$B$15)+$B$13-$B$14)-$B$17*$B$16)/($A45-$B$17)/(1+$A45)^5 -> 712.65341 | E45: =B$5/(1+$A45)^1+C$5/(1+$A45)^2+D$5/(1+$A45)^3+E$5/(1+$A45)^4+F$5/(1+$A45)^5+$B$11*((1+$B$17)*((E$42-$B$13)*(1-$B$15)+$B$13-$B$14)-$B$17*$B$16)/($A45-$B$17)/(1+$A45)^5 -> 772.32588 | F45: =B$5/(1+$A45)^1+C$5/(1+$A45)^2+D$5/(1+$A45)^3+E$5/(1+$A45)^4+F$5/(1+$A45)^5+$B$11*((1+$B$17)*((F$42-$B$13)*(1-$B$15)+$B$13-$B$14)-$B$17*$B$16)/($A45-$B$17)/(1+$A45)^5 -> 831.99836
A46: =$B$18+(1)*Assumptions!$B$94 -> 0.0932196 | B46: =B$5/(1+$A46)^1+C$5/(1+$A46)^2+D$5/(1+$A46)^3+E$5/(1+$A46)^4+F$5/(1+$A46)^5+$B$11*((1+$B$17)*((B$42-$B$13)*(1-$B$15)+$B$13-$B$14)-$B$17*$B$16)/($A46-$B$17)/(1+$A46)^5 -> 547.4561 | C46: =B$5/(1+$A46)^1+C$5/(1+$A46)^2+D$5/(1+$A46)^3+E$5/(1+$A46)^4+F$5/(1+$A46)^5+$B$11*((1+$B$17)*((C$42-$B$13)*(1-$B$15)+$B$13-$B$14)-$B$17*$B$16)/($A46-$B$17)/(1+$A46)^5 -> 601.16388 | D46: =B$5/(1+$A46)^1+C$5/(1+$A46)^2+D$5/(1+$A46)^3+E$5/(1+$A46)^4+F$5/(1+$A46)^5+$B$11*((1+$B$17)*((D$42-$B$13)*(1-$B$15)+$B$13-$B$14)-$B$17*$B$16)/($A46-$B$17)/(1+$A46)^5 -> 654.87166 | E46: =B$5/(1+$A46)^1+C$5/(1+$A46)^2+D$5/(1+$A46)^3+E$5/(1+$A46)^4+F$5/(1+$A46)^5+$B$11*((1+$B$17)*((E$42-$B$13)*(1-$B$15)+$B$13-$B$14)-$B$17*$B$16)/($A46-$B$17)/(1+$A46)^5 -> 708.57945 | F46: =B$5/(1+$A46)^1+C$5/(1+$A46)^2+D$5/(1+$A46)^3+E$5/(1+$A46)^4+F$5/(1+$A46)^5+$B$11*((1+$B$17)*((F$42-$B$13)*(1-$B$15)+$B$13-$B$14)-$B$17*$B$16)/($A46-$B$17)/(1+$A46)^5 -> 762.28723
A47: =$B$18+(2)*Assumptions!$B$94 -> 0.0982196 | B47: =B$5/(1+$A47)^1+C$5/(1+$A47)^2+D$5/(1+$A47)^3+E$5/(1+$A47)^4+F$5/(1+$A47)^5+$B$11*((1+$B$17)*((B$42-$B$13)*(1-$B$15)+$B$13-$B$14)-$B$17*$B$16)/($A47-$B$17)/(1+$A47)^5 -> 508.28278 | C47: =B$5/(1+$A47)^1+C$5/(1+$A47)^2+D$5/(1+$A47)^3+E$5/(1+$A47)^4+F$5/(1+$A47)^5+$B$11*((1+$B$17)*((C$42-$B$13)*(1-$B$15)+$B$13-$B$14)-$B$17*$B$16)/($A47-$B$17)/(1+$A47)^5 -> 556.93144 | D47: =B$5/(1+$A47)^1+C$5/(1+$A47)^2+D$5/(1+$A47)^3+E$5/(1+$A47)^4+F$5/(1+$A47)^5+$B$11*((1+$B$17)*((D$42-$B$13)*(1-$B$15)+$B$13-$B$14)-$B$17*$B$16)/($A47-$B$17)/(1+$A47)^5 -> 605.58011 | E47: =B$5/(1+$A47)^1+C$5/(1+$A47)^2+D$5/(1+$A47)^3+E$5/(1+$A47)^4+F$5/(1+$A47)^5+$B$11*((1+$B$17)*((E$42-$B$13)*(1-$B$15)+$B$13-$B$14)-$B$17*$B$16)/($A47-$B$17)/(1+$A47)^5 -> 654.22877 | F47: =B$5/(1+$A47)^1+C$5/(1+$A47)^2+D$5/(1+$A47)^3+E$5/(1+$A47)^4+F$5/(1+$A47)^5+$B$11*((1+$B$17)*((F$42-$B$13)*(1-$B$15)+$B$13-$B$14)-$B$17*$B$16)/($A47-$B$17)/(1+$A47)^5 -> 702.87743
A50: What you need to believe: reaching the announced enterprise value (a CHECK, not a target)
A51: Announced enterprise value (EUR m) | B51: =Assumptions!$B$10 -> 1200
A52: Gap: announced EV less this DCF (EUR m) | B52: =B51-B24 -> 487.34659
A53: Terminal value (undiscounted) the announced EV would require | B53: =(B51-B23)/F7 -> 1592.9471
A54: Required terminal-year free cash flow per EUR of revenue, A* | B54: =(B53*(B18-B17)/B11+B17*B16)/(1+B17) -> 0.2769877
A55: REQUIRED TERMINAL EBITDA MARGIN (holding growth and WACC) | B55: =(B54-B13+B14)/(1-B15)+B13 -> 0.38670819
A56: vs the case terminal margin (percentage points) | B56: =B55-B12 -> 0.16334049
A57: vs the reported FY2025 margin (percentage points) | B57: =B55-Assumptions!$B$24 -> 0.16334049
A58: REQUIRED TERMINAL GROWTH (holding margin and WACC) | B58: =(B53*B18-B11*B19)/(B11*(B19-B16)+B53) -> 0.057161296
A59: vs the case terminal growth (percentage points) | B59: =B58-B17 -> 0.027161296
A60: Check: EV recomputed at the required margin (must equal the announced EV) | B60: =B$5/(1+$B$18)^1+C$5/(1+$B$18)^2+D$5/(1+$B$18)^3+E$5/(1+$B$18)^4+F$5/(1+$B$18)^5+$B$11*((1+$B$17)*(($B$55-$B$13)*(1-$B$15)+$B$13-$B$14)-$B$17*$B$16)/($B$18-$B$17)/(1+$B$18)^5 -> 1200
A61: Check: EV recomputed at the required growth (must equal the announced EV) | B61: =B$5/(1+$B$18)^1+C$5/(1+$B$18)^2+D$5/(1+$B$18)^3+E$5/(1+$B$18)^4+F$5/(1+$B$18)^5+$B$11*((1+$B$58)*(($B$12-$B$13)*(1-$B$15)+$B$13-$B$14)-$B$58*$B$16)/($B$18-$B$58)/(1+$B$18)^5 -> 1200
A62: Reading | B62: =IF(B58>=B18,"Required growth reaches or exceeds WACC: not attainable by growth alone",IF(B55>0.6,"Required margin is implausibly high","Required margin and growth are mathematically attainable; judge plausibility against the reported ~22% and Nippon Paint's ~26% 2026 projection")) -> Required margin and growth are mathematically attainable; judge plausibility against the reported ~22% and Nippon Paint's ~26% 2026 projection

Sheet Cases
A1: Cases: all three cases computed side by side (independent of the selector)
A2: Each block re-runs the same chain as Carveout_PnL / DCF_Valuation from the case drivers. The check at the bottom proves the active-case DCF equals the matching block here. The Valuation workbook links to this sheet.
A4: Summary (EUR m) | B4: Base | C4: Buyer | D4: Downside
A5: Enterprise value | B5: =$B$35 -> 712.65341 | C5: =$B$61 -> 853.74496 | D5: =$B$87 -> 586.19842
A6: EV, Low (WACC + step, g - step) | B6: =$B$37 -> 618.1059 | C6: =$B$63 -> 741.2877 | D6: =$B$89 -> 509.65832
A7: EV, High (WACC - step, g + step) | B7: =$B$38 -> 845.99667 | C7: =$B$64 -> 1012.3308 | D7: =$B$90 -> 694.09726
A8: TV as % of EV | B8: =$B$36 -> 0.78082369 | C8: =$B$62 -> 0.77307113 | D8: =$B$88 -> 0.76977312
A9: FY2026E revenue | B9: =$B$17 -> 271.6 | C9: =$B$43 -> 293.33333 | D9: =$B$69 -> 266.42667
A10: FY2026E EBITDA | B10: =$B$19 -> 60.666667 | C10: =$B$45 -> 76.266667 | D10: =$B$71 -> 56.846844
A11: Terminal EBITDA margin (FY2030E) | B11: =$B$31 -> 0.2233677 | C11: =$B$57 -> 0.24168385 | D11: =$B$83 -> 0.2033677
A12: Integrity check: active-case DCF_Valuation EV minus this sheet's matching case (must be 0) | B12: =DCF_Valuation!B24-CHOOSE(Assumptions!$B$35,B5,C5,D5) -> 0 | C12: =IF(ABS(B12)<0.000001,"OK","CHECK FAILED") -> OK
A14: Case 1: Base
A15: EUR m | B15: FY2026E | C15: FY2027E | D15: FY2028E | E15: FY2029E | F15: FY2030E
A16: Revenue growth | B16: =Case_Drivers!$B$6 -> 0.05 | C16: =Case_Drivers!$C$6 -> 0.05 | D16: =Case_Drivers!$D$6 -> 0.05 | E16: =Case_Drivers!$E$6 -> 0.05 | F16: =Case_Drivers!$F$6 -> 0.05
A17: Revenue | B17: =Assumptions!$B$26*(1+B16) -> 271.6 | C17: =B17*(1+C16) -> 285.18 | D17: =C17*(1+D16) -> 299.439 | E17: =D17*(1+E16) -> 314.41095 | F17: =E17*(1+F16) -> 330.1315
A18: EBITDA margin | B18: =Case_Drivers!$B$12 -> 0.2233677 | C18: =Case_Drivers!$C$12 -> 0.2233677 | D18: =Case_Drivers!$D$12 -> 0.2233677 | E18: =Case_Drivers!$E$12 -> 0.2233677 | F18: =Case_Drivers!$F$12 -> 0.2233677
A19: EBITDA | B19: =B17*B18 -> 60.666667 | C19: =C17*C18 -> 63.7 | D19: =D17*D18 -> 66.885 | E19: =E17*E18 -> 70.22925 | F19: =F17*F18 -> 73.740713
A20: D&A | B20: =B17*Assumptions!$B$100 -> 6.79 | C20: =C17*Assumptions!$B$100 -> 7.1295 | D20: =D17*Assumptions!$B$100 -> 7.485975 | E20: =E17*Assumptions!$B$100 -> 7.8602738 | F20: =F17*Assumptions!$B$100 -> 8.2532874
A21: EBIT | B21: =B19-B20 -> 53.876667 | C21: =C19-C20 -> 56.5705 | D21: =D19-D20 -> 59.399025 | E21: =E19-E20 -> 62.368976 | F21: =F19-F20 -> 65.487425
A22: Cash taxes | B22: =MAX(B21,0)*Assumptions!$B$66 -> 11.874417 | C22: =MAX(C21,0)*Assumptions!$B$66 -> 12.468138 | D22: =MAX(D21,0)*Assumptions!$B$66 -> 13.091545 | E22: =MAX(E21,0)*Assumptions!$B$66 -> 13.746122 | F22: =MAX(F21,0)*Assumptions!$B$66 -> 14.433428
A23: Capex | B23: =B17*Assumptions!$B$101 -> 9.506 | C23: =C17*Assumptions!$B$102 -> 9.9813 | D23: =D17*Assumptions!$B$103 -> 8.98317 | E23: =E17*Assumptions!$B$104 -> 9.4323285 | F23: =F17*Assumptions!$B$105 -> 9.9039449
A24: Change in NWC | B24: =(B17-Assumptions!$B$26)*Working_Capital!$B$16 -> 1.8868493 | C24: =(C17-B17)*Working_Capital!$B$16 -> 1.9811918 | D24: =(D17-C17)*Working_Capital!$B$16 -> 2.0802514 | E24: =(E17-D17)*Working_Capital!$B$16 -> 2.1842639 | F24: =(F17-E17)*Working_Capital!$B$16 -> 2.2934771
A25: Separation costs | B25: =Assumptions!$B$120 -> 8 | C25: 0 | D25: 0 | E25: 0 | F25: 0
A26: Unlevered FCF | B26: =B19-B22-B23-B24-B25 -> 29.3994 | C26: =C19-C22-C23-C24-C25 -> 39.26937 | D26: =D19-D22-D23-D24-D25 -> 42.730034 | E26: =E19-E22-E23-E24-E25 -> 44.866535 | F26: =F19-F22-F23-F24-F25 -> 47.109862
A27: Discount factor | B27: =1/(1+Assumptions!$B$92)^1 -> 0.91893217 | C27: =1/(1+Assumptions!$B$92)^2 -> 0.84443634 | D27: =1/(1+Assumptions!$B$92)^3 -> 0.77597972 | E27: =1/(1+Assumptions!$B$92)^4 -> 0.71307272 | F27: =1/(1+Assumptions!$B$92)^5 -> 0.65526547
A28: PV of FCF | B28: =B26*B27 -> 27.016054 | C28: =C26*C27 -> 33.160483 | D28: =D26*D27 -> 33.157639 | E28: =E26*E27 -> 31.993103 | F28: =F26*F27 -> 30.869466
A30: Sum of PV of FCF | B30: =SUM(B28:F28) -> 156.19674
A31: Terminal EBITDA margin (FY2030E case margin) | B31: =F18 -> 0.2233677
A32: Terminal-year free cash flow per EUR of FY2030E revenue, A | B32: =(B31-Assumptions!$B$100)*(1-Assumptions!$B$66)+Assumptions!$B$100-Assumptions!$B$106 -> 0.14964746
A33: Terminal value | B33: =F17*((1+Assumptions!$B$93)*B32-Assumptions!$B$93*Working_Capital!$B$16)/(Assumptions!$B$92-Assumptions!$B$93) -> 849.20798
A34: PV of terminal value | B34: =B33*F27 -> 556.45666
A35: ENTERPRISE VALUE (EUR m) | B35: =B30+B34 -> 712.65341
A36: TV as % of EV | B36: =B34/B35 -> 0.78082369
A37: EV at WACC + step, g - step (Low) | B37: =B26/(1+(Assumptions!$B$92+Assumptions!$B$94))^1+C26/(1+(Assumptions!$B$92+Assumptions!$B$94))^2+D26/(1+(Assumptions!$B$92+Assumptions!$B$94))^3+E26/(1+(Assumptions!$B$92+Assumptions!$B$94))^4+F26/(1+(Assumptions!$B$92+Assumptions!$B$94))^5+F17*((1+(Assumptions!$B$93-Assumptions!$B$95))*B32-(Assumptions!$B$93-Assumptions!$B$95)*Working_Capital!$B$16)/((Assumptions!$B$92+Assumptions!$B$94)-(Assumptions!$B$93-Assumptions!$B$95))/(1+(Assumptions!$B$92+Assumptions!$B$94))^5 -> 618.1059
A38: EV at WACC - step, g + step (High) | B38: =B26/(1+(Assumptions!$B$92-Assumptions!$B$94))^1+C26/(1+(Assumptions!$B$92-Assumptions!$B$94))^2+D26/(1+(Assumptions!$B$92-Assumptions!$B$94))^3+E26/(1+(Assumptions!$B$92-Assumptions!$B$94))^4+F26/(1+(Assumptions!$B$92-Assumptions!$B$94))^5+F17*((1+(Assumptions!$B$93+Assumptions!$B$95))*B32-(Assumptions!$B$93+Assumptions!$B$95)*Working_Capital!$B$16)/((Assumptions!$B$92-Assumptions!$B$94)-(Assumptions!$B$93+Assumptions!$B$95))/(1+(Assumptions!$B$92-Assumptions!$B$94))^5 -> 845.99667
A39: Reverse DCF: terminal value (undiscounted) needed to reach the announced EV | B39: =(Assumptions!$B$10-B30)/F27 -> 1592.9471
A40: Case 2: Buyer | B40: =(((B39*(Assumptions!$B$92-Assumptions!$B$93)/F17+Assumptions!$B$93*Working_Capital!$B$16)/(1+Assumptions!$B$93))-Assumptions!$B$100+Assumptions!$B$106)/(1-Assumptions!$B$66)+Assumptions!$B$100 -> 0.38670819
A41: EUR m | B41: FY2026E | C41: FY2027E | D41: FY2028E | E41: FY2029E | F41: FY2030E
A42: Revenue growth | B42: =Case_Drivers!$B$7 -> 0.13402062 | C42: =Case_Drivers!$C$7 -> 0.05 | D42: =Case_Drivers!$D$7 -> 0.05 | E42: =Case_Drivers!$E$7 -> 0.05 | F42: =Case_Drivers!$F$7 -> 0.05
A43: Revenue | B43: =Assumptions!$B$26*(1+B42) -> 293.33333 | C43: =B43*(1+C42) -> 308 | D43: =C43*(1+D42) -> 323.4 | E43: =D43*(1+E42) -> 339.57 | F43: =E43*(1+F42) -> 356.5485
A44: EBITDA margin | B44: =Case_Drivers!$B$13 -> 0.26 | C44: =Case_Drivers!$C$13 -> 0.25542096 | D44: =Case_Drivers!$D$13 -> 0.25084192 | E44: =Case_Drivers!$E$13 -> 0.24626289 | F44: =Case_Drivers!$F$13 -> 0.24168385
A45: EBITDA | B45: =B43*B44 -> 76.266667 | C45: =C43*C44 -> 78.669656 | D45: =D43*D44 -> 81.122278 | E45: =E43*E44 -> 83.623488 | F45: =F43*F44 -> 86.172014
A46: D&A | B46: =B43*Assumptions!$B$100 -> 7.3333333 | C46: =C43*Assumptions!$B$100 -> 7.7 | D46: =D43*Assumptions!$B$100 -> 8.085 | E46: =E43*Assumptions!$B$100 -> 8.48925 | F46: =F43*Assumptions!$B$100 -> 8.9137125
A47: EBIT | B47: =B45-B46 -> 68.933333 | C47: =C45-C46 -> 70.969656 | D47: =D45-D46 -> 73.037278 | E47: =E45-E46 -> 75.134238 | F47: =F45-F46 -> 77.258301
A48: Cash taxes | B48: =MAX(B47,0)*Assumptions!$B$66 -> 15.192907 | C48: =MAX(C47,0)*Assumptions!$B$66 -> 15.641712 | D48: =MAX(D47,0)*Assumptions!$B$66 -> 16.097416 | E48: =MAX(E47,0)*Assumptions!$B$66 -> 16.559586 | F48: =MAX(F47,0)*Assumptions!$B$66 -> 17.02773
A49: Capex | B49: =B43*Assumptions!$B$101 -> 10.266667 | C49: =C43*Assumptions!$B$102 -> 10.78 | D49: =D43*Assumptions!$B$103 -> 9.702 | E49: =E43*Assumptions!$B$104 -> 10.1871 | F49: =F43*Assumptions!$B$105 -> 10.696455
A50: Change in NWC | B50: =(B43-Assumptions!$B$26)*Working_Capital!$B$16 -> 5.0575342 | C50: =(C43-B43)*Working_Capital!$B$16 -> 2.139726 | D50: =(D43-C43)*Working_Capital!$B$16 -> 2.2467123 | E50: =(E43-D43)*Working_Capital!$B$16 -> 2.3590479 | F50: =(F43-E43)*Working_Capital!$B$16 -> 2.4770003
A51: Separation costs | B51: =Assumptions!$B$120 -> 8 | C51: 0 | D51: 0 | E51: 0 | F51: 0
A52: Unlevered FCF | B52: =B45-B48-B49-B50-B51 -> 37.749559 | C52: =C45-C48-C49-C50-C51 -> 50.108218 | D52: =D45-D48-D49-D50-D51 -> 53.07615 | E52: =E45-E48-E49-E50-E51 -> 54.517754 | F52: =F45-F48-F49-F50-F51 -> 55.970829
A53: Discount factor | B53: =1/(1+Assumptions!$B$92)^1 -> 0.91893217 | C53: =1/(1+Assumptions!$B$92)^2 -> 0.84443634 | D53: =1/(1+Assumptions!$B$92)^3 -> 0.77597972 | E53: =1/(1+Assumptions!$B$92)^4 -> 0.71307272 | F53: =1/(1+Assumptions!$B$92)^5 -> 0.65526547
A54: PV of FCF | B54: =B52*B53 -> 34.689284 | C54: =C52*C53 -> 42.3132 | D54: =D52*D53 -> 41.186016 | E54: =E52*E53 -> 38.875124 | F54: =F52*F53 -> 36.675751
A56: Sum of PV of FCF | B56: =SUM(B54:F54) -> 193.73937
A57: Terminal EBITDA margin (FY2030E case margin) | B57: =F44 -> 0.24168385
A58: Terminal-year free cash flow per EUR of FY2030E revenue, A | B58: =(B57-Assumptions!$B$100)*(1-Assumptions!$B$66)+Assumptions!$B$100-Assumptions!$B$106 -> 0.16392673
A59: Terminal value | B59: =F43*((1+Assumptions!$B$93)*B58-Assumptions!$B$93*Working_Capital!$B$16)/(Assumptions!$B$92-Assumptions!$B$93) -> 1007.2339
A60: PV of terminal value | B60: =B59*F53 -> 660.00558
A61: ENTERPRISE VALUE (EUR m) | B61: =B56+B60 -> 853.74496
A62: TV as % of EV | B62: =B60/B61 -> 0.77307113
A63: EV at WACC + step, g - step (Low) | B63: =B52/(1+(Assumptions!$B$92+Assumptions!$B$94))^1+C52/(1+(Assumptions!$B$92+Assumptions!$B$94))^2+D52/(1+(Assumptions!$B$92+Assumptions!$B$94))^3+E52/(1+(Assumptions!$B$92+Assumptions!$B$94))^4+F52/(1+(Assumptions!$B$92+Assumptions!$B$94))^5+F43*((1+(Assumptions!$B$93-Assumptions!$B$95))*B58-(Assumptions!$B$93-Assumptions!$B$95)*Working_Capital!$B$16)/((Assumptions!$B$92+Assumptions!$B$94)-(Assumptions!$B$93-Assumptions!$B$95))/(1+(Assumptions!$B$92+Assumptions!$B$94))^5 -> 741.2877
A64: EV at WACC - step, g + step (High) | B64: =B52/(1+(Assumptions!$B$92-Assumptions!$B$94))^1+C52/(1+(Assumptions!$B$92-Assumptions!$B$94))^2+D52/(1+(Assumptions!$B$92-Assumptions!$B$94))^3+E52/(1+(Assumptions!$B$92-Assumptions!$B$94))^4+F52/(1+(Assumptions!$B$92-Assumptions!$B$94))^5+F43*((1+(Assumptions!$B$93+Assumptions!$B$95))*B58-(Assumptions!$B$93+Assumptions!$B$95)*Working_Capital!$B$16)/((Assumptions!$B$92-Assumptions!$B$94)-(Assumptions!$B$93+Assumptions!$B$95))/(1+(Assumptions!$B$92-Assumptions!$B$94))^5 -> 1012.3308
A65: Reverse DCF: terminal value (undiscounted) needed to reach the announced EV | B65: =(Assumptions!$B$10-B56)/F53 -> 1535.6534
A66: Case 3: Downside | B66: =(((B65*(Assumptions!$B$92-Assumptions!$B$93)/F43+Assumptions!$B$93*Working_Capital!$B$16)/(1+Assumptions!$B$93))-Assumptions!$B$100+Assumptions!$B$106)/(1-Assumptions!$B$66)+Assumptions!$B$100 -> 0.3491373
A67: EUR m | B67: FY2026E | C67: FY2027E | D67: FY2028E | E67: FY2029E | F67: FY2030E
A68: Revenue growth | B68: =Case_Drivers!$B$8 -> 0.03 | C68: =Case_Drivers!$C$8 -> 0.03 | D68: =Case_Drivers!$D$8 -> 0.03 | E68: =Case_Drivers!$E$8 -> 0.03 | F68: =Case_Drivers!$F$8 -> 0.03
A69: Revenue | B69: =Assumptions!$B$26*(1+B68) -> 266.42667 | C69: =B69*(1+C68) -> 274.41947 | D69: =C69*(1+D68) -> 282.65205 | E69: =D69*(1+E68) -> 291.13161 | F69: =E69*(1+F68) -> 299.86556
A70: EBITDA margin | B70: =Case_Drivers!$B$14 -> 0.2133677 | C70: =Case_Drivers!$C$14 -> 0.2033677 | D70: =Case_Drivers!$D$14 -> 0.2033677 | E70: =Case_Drivers!$E$14 -> 0.2033677 | F70: =Case_Drivers!$F$14 -> 0.2033677
A71: EBITDA | B71: =B69*B70 -> 56.846844 | C71: =C69*C70 -> 55.808055 | D71: =D69*D70 -> 57.482297 | E71: =E69*E70 -> 59.206766 | F71: =F69*F70 -> 60.982969
A72: D&A | B72: =B69*Assumptions!$B$100 -> 6.6606667 | C72: =C69*Assumptions!$B$100 -> 6.8604867 | D72: =D69*Assumptions!$B$100 -> 7.0663013 | E72: =E69*Assumptions!$B$100 -> 7.2782903 | F72: =F69*Assumptions!$B$100 -> 7.496639
A73: EBIT | B73: =B71-B72 -> 50.186178 | C73: =C71-C72 -> 48.947568 | D73: =D71-D72 -> 50.415995 | E73: =E71-E72 -> 51.928475 | F73: =F71-F72 -> 53.48633
A74: Cash taxes | B74: =MAX(B73,0)*Assumptions!$B$66 -> 11.061034 | C74: =MAX(C73,0)*Assumptions!$B$66 -> 10.788044 | D74: =MAX(D73,0)*Assumptions!$B$66 -> 11.111685 | E74: =MAX(E73,0)*Assumptions!$B$66 -> 11.445036 | F74: =MAX(F73,0)*Assumptions!$B$66 -> 11.788387
A75: Capex | B75: =B69*Assumptions!$B$101 -> 9.3249333 | C75: =C69*Assumptions!$B$102 -> 9.6046813 | D75: =D69*Assumptions!$B$103 -> 8.4795615 | E75: =E69*Assumptions!$B$104 -> 8.7339484 | F75: =F69*Assumptions!$B$105 -> 8.9959668
A76: Change in NWC | B76: =(B69-Assumptions!$B$26)*Working_Capital!$B$16 -> 1.1321096 | C76: =(C69-B69)*Working_Capital!$B$16 -> 1.1660729 | D76: =(D69-C69)*Working_Capital!$B$16 -> 1.2010551 | E76: =(E69-D69)*Working_Capital!$B$16 -> 1.2370867 | F76: =(F69-E69)*Working_Capital!$B$16 -> 1.2741993
A77: Separation costs | B77: =Assumptions!$B$120 -> 8 | C77: 0 | D77: 0 | E77: 0 | F77: 0
A78: Unlevered FCF | B78: =B71-B74-B75-B76-B77 -> 27.328768 | C78: =C71-C74-C75-C76-C77 -> 34.249257 | D78: =D71-D74-D75-D76-D77 -> 36.689995 | E78: =E71-E74-E75-E76-E77 -> 37.790695 | F78: =F71-F74-F75-F76-F77 -> 38.924415
A79: Discount factor | B79: =1/(1+Assumptions!$B$92)^1 -> 0.91893217 | C79: =1/(1+Assumptions!$B$92)^2 -> 0.84443634 | D79: =1/(1+Assumptions!$B$92)^3 -> 0.77597972 | E79: =1/(1+Assumptions!$B$92)^4 -> 0.71307272 | F79: =1/(1+Assumptions!$B$92)^5 -> 0.65526547
A80: PV of FCF | B80: =B78*B79 -> 25.113284 | C80: =C78*C79 -> 28.921317 | D80: =D78*D79 -> 28.470692 | E80: =E78*E79 -> 26.947514 | F80: =F78*F79 -> 25.505825
A82: Sum of PV of FCF | B82: =SUM(B80:F80) -> 134.95863
A83: Terminal EBITDA margin (FY2030E case margin) | B83: =F70 -> 0.2033677
A84: Terminal-year free cash flow per EUR of FY2030E revenue, A | B84: =(B83-Assumptions!$B$100)*(1-Assumptions!$B$66)+Assumptions!$B$100-Assumptions!$B$106 -> 0.13405546
A85: Terminal value | B85: =F69*((1+Assumptions!$B$93)*B84-Assumptions!$B$93*Working_Capital!$B$16)/(Assumptions!$B$92-Assumptions!$B$93) -> 688.63661
A86: PV of terminal value | B86: =B85*F79 -> 451.23979
A87: ENTERPRISE VALUE (EUR m) | B87: =B82+B86 -> 586.19842
A88: TV as % of EV | B88: =B86/B87 -> 0.76977312
A89: EV at WACC + step, g - step (Low) | B89: =B78/(1+(Assumptions!$B$92+Assumptions!$B$94))^1+C78/(1+(Assumptions!$B$92+Assumptions!$B$94))^2+D78/(1+(Assumptions!$B$92+Assumptions!$B$94))^3+E78/(1+(Assumptions!$B$92+Assumptions!$B$94))^4+F78/(1+(Assumptions!$B$92+Assumptions!$B$94))^5+F69*((1+(Assumptions!$B$93-Assumptions!$B$95))*B84-(Assumptions!$B$93-Assumptions!$B$95)*Working_Capital!$B$16)/((Assumptions!$B$92+Assumptions!$B$94)-(Assumptions!$B$93-Assumptions!$B$95))/(1+(Assumptions!$B$92+Assumptions!$B$94))^5 -> 509.65832
A90: EV at WACC - step, g + step (High) | B90: =B78/(1+(Assumptions!$B$92-Assumptions!$B$94))^1+C78/(1+(Assumptions!$B$92-Assumptions!$B$94))^2+D78/(1+(Assumptions!$B$92-Assumptions!$B$94))^3+E78/(1+(Assumptions!$B$92-Assumptions!$B$94))^4+F78/(1+(Assumptions!$B$92-Assumptions!$B$94))^5+F69*((1+(Assumptions!$B$93+Assumptions!$B$95))*B84-(Assumptions!$B$93+Assumptions!$B$95)*Working_Capital!$B$16)/((Assumptions!$B$92-Assumptions!$B$94)-(Assumptions!$B$93+Assumptions!$B$95))/(1+(Assumptions!$B$92-Assumptions!$B$94))^5 -> 694.09726
A91: Reverse DCF: terminal value (undiscounted) needed to reach the announced EV | B91: =(Assumptions!$B$10-B82)/F79 -> 1625.3586
A92: Terminal EBITDA margin needed, holding terminal growth | B92: =(((B91*(Assumptions!$B$92-Assumptions!$B$93)/F69+Assumptions!$B$93*Working_Capital!$B$16)/(1+Assumptions!$B$93))-Assumptions!$B$100+Assumptions!$B$106)/(1-Assumptions!$B$66)+Assumptions!$B$100 -> 0.42985523
A93: Terminal growth needed, holding the case terminal margin | B93: =(B91*Assumptions!$B$92-F69*B84)/(F69*(B84-Working_Capital!$B$16)+B91) -> 0.063626374

Sheet Sources
A1: Source ID | B1: Source | C1: URL / reference | D1: Used for
A2: SRC-001 | B2: ION Analytics / Mergermarket, 'AkzoNobel taps Goldman Sachs for sale of Southeast Asia paints assets' | C2: ionanalytics.com (September 2026 process article) | D2: ASEAN market growth ~5% (base-case growth anchor)
A3: SRC-016 | B3: OECD Corporate Tax Statistics 2026 / Trading Economics / Thaicore | C3: oecd.org; tradingeconomics.com; thaicore.co.th | D3: Statutory CIT: Indonesia, Thailand, Vietnam, Malaysia
A4: SRC-034 | B4: Yahoo Finance (yfinance), live comps pull | C4: finance.yahoo.com, 2026-09-18 | D4: Peer-median beta 0.821
A5: SRC-037 | B5: AkzoNobel media release, 5 Oct 2026 | C5: akzonobel.com/en/media/media-releases/akzonobel-to-sell-decorative-paints-south-east-asia-business-to-nippon-paint | D5: EV, 21x, proceeds, perimeter, timing
A6: SRC-038 | B6: AkzoNobel Form 6-K, Exhibit 99.1 (SEC EDGAR) | C6: sec.gov/Archives/edgar/data/0000003124/000095010326015189/dp254601_ex9901.htm | D6: Same facts, regulatory filing
A7: SRC-039 | B7: PCI Magazine, 'AkzoNobel to sell Southeast Asia decorative paints business to Nippon Paint for $1.35 billion' | C7: pcimag.com/articles/115350-... | D7: FY24/FY25 financials; the ONLY source for the 2026 revenue (>~$330m) and ~26% margin
A8: SRC-040 | B8: Business Today Malaysia; DealStreetAsia, 5 Oct 2026 | C8: businesstoday.com.my; dealstreetasia.com | D8: Corroborates price, perimeter, proceeds (no revenue/EBITDA)
A9: SRC-041 | B9: Investing.com, 'AkzoNobel rises as Nippon Paint buys Asia-Pacific unit for $1.35 bln' | C9: investing.com/news/stock-market-news/nippon-paint-shares-rise-on-135-billion-deal-for-akzos-southeast-asia-paint-arm-4930991 | D9: FY2025 revenue/EBITDA and 'roughly 16x projected 2026 EBITDA', attributed to Nippon Paint
A10: SRC-042 | B10: Yahoo Finance Singapore / MT Newswires, 'Nippon Paint to Buy AkzoNobel's Southeast Asia, Australia Units for $1.35 Billion' | C10: sg.finance.yahoo.com/news/nippon-paint-buy-akzonobel-apos-014603443.html | D10: FY2024 and FY2025 revenue/EBITDA, attributed to the Nippon Paint press release
A11: SRC-043 | B11: Yahoo Finance UK, 'Nippon Paint shares rise on $1.35 billion deal for Akzo's Southeast Asia paint arm' | C11: uk.finance.yahoo.com/news/nippon-paint-shares-rise-1-033610211.html | D11: FY2025 revenue/EBITDA and the 16x multiple, attributed to Nippon Paint
A12: SRC-044 | B12: IRAS, Corporate Income Tax Rates (Singapore) | C12: iras.gov.sg/quick-links/tax-rates/corporate-income-tax-rates | D12: Singapore CIT 17%
... A14: SRC-046 | B14: Australian Taxation Office, Company tax rates 2025-26 | C14: ato.gov.au/tax-rates-and-codes/company-tax-rates/tax-rates-2025-26 | D14: Australia company tax 30% (25% only for base-rate entities)
A16: Tax-rate and corroboration sources were confirmed through web searches that returned the authoritative pages' content; the primary Nippon Paint release itself could not be accessed.
